{"Away Team Shots": 6, "Away Team Red Cards": 0, "Home Team": "Watford", "Home Team Yellow Cards": 4, "Away Team Fouls Committed": 9, "Away Team Corners": 1, "Referee": "M Oliver", "Home Team Fouls Committed": 10, "Half Time Home Team Goals": 0, "Date": "28-10-2017", "Half Time Away Team Goals": 1, "Home Team Red Cards": 0, "Away Team": "Stoke City", "Home Team Shots": 13, "Div": "E0", "Home Team Corners": 8, "Full Time Away Team Goals": 1, "Full Time Result": "A", "Away Team Shots on Target": 2, "Full Time Home Team Goals": 0, "Half Time Result": "A", "Away Team Yellow Cards": 4, "Home Team Shots on Target": 0}