{"Stats": {"Full Time Result": "D", "Away Team Corners": 4, "Referee": "S Attwell", "Home Team Fouls Committed": 12, "Home Team Corners": 7, "Away Team Shots": 10, "Away Team Red Cards": 0, "Home Team Red Cards": 0, "Half Time Away Team Goals": 1, "Full Time Home Team Goals": 3, "Away Team Yellow Cards": 4, "Away Team Shots on Target": 5, "Half Time Home Team Goals": 1, "Half Time Result": "D", "Home Team Yellow Cards": 3, "Home Team Shots": 26, "Div": "E0", "Away Team Fouls Committed": 14, "Home Team Shots on Target": 10, "Full Time Away Team Goals": 3}, "Description": "Foul by Pablo Zabaleta (West Ham United). at minute 3. Ryan Fraser (Bournemouth) wins a free kick on the left wing. at minute 3. Corner,  Bournemouth. Conceded by Angelo Ogbonna. at minute 4. Attempt missed. Simon Francis (Bournemouth) header from a difficult angle on the right is just a bit too high. Assisted by Jordon Ibe with a cross following a corner. at minute 4. Foul by Joshua King (Bournemouth). at minute 6. Pedro Obiang (West Ham United) wins a free kick in the defensive half. at minute 6. Corner,  West Ham United. Conceded by Adam Smith. at minute 7. Goal!  Bournemouth 0, West Ham United 1. James Collins (West Ham United) header from the right side of the six yard box to the bottom right corner. Assisted by Aaron Cresswell with a cross following a corner. at minute 7. Foul by Arthur Masuaku (West Ham United). at minute 9. Simon Francis (Bournemouth) wins a free kick in the defensive half. at minute 9. Cheikhou Kouyaté (West Ham United) wins a free kick in the defensive half. at minute 11. Foul by Callum Wilson (Bournemouth). at minute 11. Foul by Pedro Obiang (West Ham United). at minute 13. Joshua King (Bournemouth) wins a free kick in the attacking half. at minute 13. Foul by Pablo Zabaleta (West Ham United). at minute 13. Ryan Fraser (Bournemouth) wins a free kick on the left wing. at minute 13. Attempt missed. Joshua King (Bournemouth) left footed shot from the centre of the box misses to the left. Assisted by Callum Wilson with a cross. at minute 16. Corner,  West Ham United. Conceded by Nathan Aké. at minute 17. Attempt missed. André Ayew (West Ham United) left footed shot from the centre of the box is close, but misses to the left. Assisted by Arthur Masuaku with a cross. at minute 20. Attempt missed. Joshua King (Bournemouth) right footed shot from the centre of the box is close, but misses to the right. Assisted by Ryan Fraser. at minute 22. Attempt blocked. Jordon Ibe (Bournemouth) right footed shot from the centre of the box is blocked. at minute 23. Attempt saved. Adam Smith (Bournemouth) right footed shot from outside the box is saved in the top centre of the goal. at minute 23. Corner,  Bournemouth. Conceded by Adrián. at minute 23. Aaron Cresswell (West Ham United) wins a free kick in the defensive half. at minute 25. Foul by Callum Wilson (Bournemouth). at minute 25. Offside, West Ham United. Aaron Cresswell tries a through ball, but Marko Arnautovic is caught offside. at minute 25. Arthur Masuaku (West Ham United) wins a free kick in the defensive half. at minute 26. Foul by Simon Francis (Bournemouth). at minute 26. Offside, West Ham United. Aaron Cresswell tries a through ball, but Marko Arnautovic is caught offside. at minute 27. Foul by André Ayew (West Ham United). at minute 29. Ryan Fraser (Bournemouth) wins a free kick in the attacking half. at minute 29. Goal!  Bournemouth 1, West Ham United 1. Dan Gosling (Bournemouth) left footed shot from the centre of the box to the centre of the goal. Assisted by Joshua King following a set piece situation. at minute 29. Cheikhou Kouyaté (West Ham United) wins a free kick on the left wing. at minute 31. Foul by Simon Francis (Bournemouth). at minute 31. Delay in match Cheikhou Kouyaté (West Ham United) because of an injury. at minute 31. Simon Francis (Bournemouth) is shown the yellow card for a bad foul. at minute 32. Delay over. They are ready to continue. at minute 35. Adam Smith (Bournemouth) wins a free kick on the left wing. at minute 36. Foul by Pablo Zabaleta (West Ham United). at minute 36. Pablo Zabaleta (West Ham United) is shown the yellow card. at minute 37. Foul by Pedro Obiang (West Ham United). at minute 39. Jordon Ibe (Bournemouth) wins a free kick in the attacking half. at minute 39. Attempt blocked. Ryan Fraser (Bournemouth) left footed shot from outside the box is blocked. Assisted by Jordon Ibe. at minute 40. André Ayew (West Ham United) wins a free kick in the defensive half. at minute 41. Foul by Adam Smith (Bournemouth). at minute 41. Attempt missed. Manuel Lanzini (West Ham United) right footed shot from the centre of the box misses to the right. Assisted by Marko Arnautovic. at minute 44. Foul by Marko Arnautovic (West Ham United). at minute 47. Steve Cook (Bournemouth) wins a free kick on the right wing. at minute 47. Attempt missed. Joshua King (Bournemouth) header from the centre of the box misses to the left. Assisted by Jordon Ibe with a cross following a set piece situation. at minute 47. Attempt blocked. Nathan Aké (Bournemouth) header from the centre of the box is blocked. Assisted by Ryan Fraser with a cross. at minute 47. Attempt blocked. Dan Gosling (Bournemouth) right footed shot from the centre of the box is blocked. Assisted by Simon Francis. at minute 47. Attempt saved. Joshua King (Bournemouth) header from the centre of the box is saved in the centre of the goal. at minute 48. Attempt missed. Steve Cook (Bournemouth) right footed shot from outside the box is high and wide to the right. Assisted by Nathan Aké. at minute 48. Attempt blocked. Arthur Masuaku (West Ham United) left footed shot from the left side of the box is blocked. Assisted by Marko Arnautovic. at minute 49. First Half ends, Bournemouth 1, West Ham United 1. at minute 50. Second Half begins Bournemouth 1, West Ham United 1. at minute 45. Foul by Lewis Cook (Bournemouth). at minute 47. Pablo Zabaleta (West Ham United) wins a free kick in the defensive half. at minute 47. Attempt missed. Callum Wilson (Bournemouth) right footed shot from outside the box misses to the left. Assisted by Joshua King. at minute 51. Corner,  West Ham United. Conceded by Joshua King. at minute 52. Attempt blocked. Manuel Lanzini (West Ham United) left footed shot from the left side of the box is blocked. Assisted by Marko Arnautovic. at minute 54. Corner,  West Ham United. Conceded by Lewis Cook. at minute 54. Dan Gosling (Bournemouth) wins a free kick in the defensive half. at minute 55. Foul by James Collins (West Ham United). at minute 55. James Collins (West Ham United) is shown the yellow card for a bad foul. at minute 55. Callum Wilson (Bournemouth) wins a free kick on the right wing. at minute 56. Foul by Aaron Cresswell (West Ham United). at minute 56. Aaron Cresswell (West Ham United) is shown the yellow card for a bad foul. at minute 56. Attempt blocked. Callum Wilson (Bournemouth) header from the left side of the box is blocked. Assisted by Jordon Ibe with a cross. at minute 57. Corner,  Bournemouth. Conceded by Pedro Obiang. at minute 57. Goal!  Bournemouth 2, West Ham United 1. Nathan Aké (Bournemouth) left footed shot from the centre of the box to the bottom left corner. Assisted by Dan Gosling following a corner. at minute 57. Substitution, West Ham United. Andy Carroll replaces Pedro Obiang. at minute 60. Substitution, West Ham United. Chicharito replaces André Ayew. at minute 61. Foul by Ryan Fraser (Bournemouth). at minute 61. Pablo Zabaleta (West Ham United) wins a free kick on the right wing. at minute 61. Attempt saved. Dan Gosling (Bournemouth) right footed shot from the right side of the box is saved in the bottom right corner. Assisted by Lewis Cook. at minute 63. Corner,  Bournemouth. Conceded by Adrián. at minute 63. Corner,  Bournemouth. Conceded by Cheikhou Kouyaté. at minute 64. Attempt missed. Nathan Aké (Bournemouth) header from the centre of the box is close, but misses to the right. Assisted by Jordon Ibe with a cross following a corner. at minute 64. Substitution, Bournemouth. Benik Afobe replaces Joshua King. at minute 65. Attempt saved. Jordon Ibe (Bournemouth) right footed shot from the right side of the box is saved in the centre of the goal. Assisted by Simon Francis. at minute 67. Arthur Masuaku (West Ham United) wins a free kick on the left wing. at minute 67. Foul by Benik Afobe (Bournemouth). at minute 67. Attempt missed. Marko Arnautovic (West Ham United) left footed shot from the centre of the box misses to the left. Assisted by Chicharito. at minute 70. Chicharito (West Ham United) wins a free kick in the attacking half. at minute 71. Foul by Lewis Cook (Bournemouth). at minute 71. Lewis Cook (Bournemouth) is shown the yellow card for a bad foul. at minute 71. Attempt missed. Ryan Fraser (Bournemouth) left footed shot from the centre of the box misses to the right. Assisted by Simon Francis with a cross. at minute 72. Callum Wilson (Bournemouth) wins a free kick in the attacking half. at minute 73. Foul by Angelo Ogbonna (West Ham United). at minute 73. Foul by Manuel Lanzini (West Ham United). at minute 74. Ryan Fraser (Bournemouth) wins a free kick in the attacking half. at minute 74. Delay in match Steve Cook (Bournemouth) because of an injury. at minute 75. Delay over. They are ready to continue. at minute 77. Attempt saved. Benik Afobe (Bournemouth) right footed shot from the left side of the six yard box is saved in the bottom left corner. Assisted by Ryan Fraser with a cross. at minute 78. Attempt saved. Benik Afobe (Bournemouth) right footed shot from the left side of the six yard box is saved in the bottom left corner. at minute 78. Corner,  Bournemouth. Conceded by Adrián. at minute 78. Substitution, West Ham United. Declan Rice replaces Pablo Zabaleta. at minute 79. Foul by Nathan Aké (Bournemouth). at minute 79. Manuel Lanzini (West Ham United) wins a free kick in the defensive half. at minute 79. Nathan Aké (Bournemouth) is shown the yellow card for a bad foul. at minute 79. Attempt saved. Andy Carroll (West Ham United) left footed shot from outside the box is saved in the bottom right corner. at minute 80. Attempt saved. Jordon Ibe (Bournemouth) right footed shot from the centre of the box is saved in the bottom right corner. Assisted by Callum Wilson. at minute 80. Corner,  Bournemouth. Conceded by Adrián. at minute 80. Goal!  Bournemouth 2, West Ham United 2. Marko Arnautovic (West Ham United) left footed shot from outside the box to the bottom left corner. at minute 81. Callum Wilson (Bournemouth) wins a free kick in the defensive half. at minute 83. Foul by Angelo Ogbonna (West Ham United). at minute 83. Attempt missed. Callum Wilson (Bournemouth) header from the centre of the box misses to the left. Assisted by Simon Francis with a cross. at minute 84. Substitution, Bournemouth. Marc Pugh replaces Ryan Fraser. at minute 86. Hand ball by Aaron Cresswell (West Ham United). at minute 87. Angelo Ogbonna (West Ham United) is shown the yellow card. at minute 87. Attempt missed. Jordon Ibe (Bournemouth) right footed shot from outside the box is too high from a direct free kick. at minute 88. Attempt saved. Chicharito (West Ham United) right footed shot from the right side of the six yard box is saved in the centre of the goal. Assisted by Arthur Masuaku with a cross. at minute 89. Goal!  Bournemouth 2, West Ham United 3. Marko Arnautovic (West Ham United) right footed shot from very close range to the bottom left corner. at minute 89. Goal!  Bournemouth 3, West Ham United 3. Callum Wilson (Bournemouth) with an attempt from very close range to the bottom right corner. Assisted by Nathan Aké with a headed pass. at minute 93. Foul by Dan Gosling (Bournemouth). at minute 95. Marko Arnautovic (West Ham United) wins a free kick in the defensive half. at minute 95. Second Half ends, Bournemouth 3, West Ham United 3. at minute 97. Match ends, Bournemouth 3, West Ham United 3. at minute 97. Match ends, Bournemouth 3, West Ham United 3. at minute 97. ", "Home Team": "AFC Bournemouth", "Away Team": "West Ham United", "Date": "26-12-2017", "Commentary": [["480715", "First Half begins.", "-", "AFC Bournemouth", "0", "0", "0", "1", "0", "0", "NA", "NA", "NA", "NA", "NA", "NA", "NA", "0", "NA", "NA", "0", "NA", "0", "0", "NA", "NA", "NA", "0", "NA", "NA", "NA", "0", "NA", "NA", "0", "NA", "0", "NA", "NA", "NA", "0", "NA", "NA", "0", "0", "NA", "NA", "NA", "0", "NA", "NA", "NA", "NA", "1", "1", "0", "NA", "NA", "NA"], ["480715", "Lineups are announced and players are warming up.", "-", "AFC Bournemouth", "0", "0", "0", "0", "0", "0", "NA", "NA", "NA", "NA", "NA", "NA", "NA", "0", "NA", "NA", "0", "NA", "0", "0", "NA", "NA", "NA", "0", "NA", "NA", "NA", "0", "NA", "NA", "0", "NA", "0", "NA", "NA", "NA", "0", "NA", "NA", "0", "0", "NA", "NA", "NA", "0", "NA", "NA", "NA", "NA", "1", "2", "0", "NA", "NA", "NA"], ["480715", "Foul by Pablo Zabaleta (West Ham United).", "3'", "AFC Bournemouth", "0", "0", "0", "0", "0", "0", "NA", "NA", "NA", "NA", "NA", "NA", "NA", "1", "Pablo Zabaleta", "West Ham United", "0", "NA", "0", "0", "NA", "NA", "NA", "0", "NA", "NA", "NA", "0", "NA", "NA", "0", "NA", "0", "NA", "NA", "NA", "0", "NA", "NA", "0", "0", "NA", "NA", "NA", "0", "NA", "NA", "NA", "NA", "1", "3", "0", "NA", "NA", "3"], ["480715", "Ryan Fraser (Bournemouth) wins a free kick on the left wing.", "3'", "AFC Bournemouth", "0", "0", "0", "0", "0", "0", "NA", "NA", "NA", "NA", "NA", "NA", "NA", "0", "NA", "NA", "0", "NA", "0", "0", "NA", "NA", "NA", "0", "NA", "NA", "NA", "0", "NA", "NA", "0", "NA", "1", "Ryan Fraser", "Bournemouth", "NA", "0", "NA", "NA", "0", "0", "NA", "NA", "NA", "0", "NA", "NA", "NA", "NA", "1", "4", "0", "NA", "NA", "3"], ["480715", "Corner,  Bournemouth. Conceded by Angelo Ogbonna.", "4'", "AFC Bournemouth", "0", "0", "0", "0", "0", "0", "NA", "NA", "NA", "NA", "NA", "NA", "NA", "0", "NA", "NA", "0", "NA", "0", "0", "NA", "NA", "NA", "0", "NA", "NA", "NA", "0", "NA", "NA", "0", "NA", "0", "NA", "NA", "NA", "1", "Bournemouth", "Angelo Ogbonna", "0", "0", "NA", "NA", "NA", "0", "NA", "NA", "NA", "NA", "1", "5", "0", "NA", "NA", "4"], ["480715", "Attempt missed. Simon Francis (Bournemouth) header from a difficult angle on the right is just a bit too high. Assisted by Jordon Ibe with a cross following a corner.", "4'", "AFC Bournemouth", "0", "0", "0", "0", "1", "0", "missed", "Simon Francis", "Bournemouth", "header", "NA", "NA", "Jordon Ibe", "0", "NA", "NA", "0", "cross", "1", "0", "NA", "NA", "NA", "0", "NA", "NA", "NA", "0", "NA", "NA", "0", "NA", "0", "NA", "NA", "NA", "0", "NA", "NA", "0", "0", "NA", "NA", "NA", "0", "NA", "NA", "NA", "NA", "1", "6", "0", "NA", "NA", "4"], ["480715", "Foul by Joshua King (Bournemouth).", "6'", "AFC Bournemouth", "0", "0", "0", "0", "0", "0", "NA", "NA", "NA", "NA", "NA", "NA", "NA", "1", "Joshua King", "Bournemouth", "0", "NA", "0", "0", "NA", "NA", "NA", "0", "NA", "NA", "NA", "0", "NA", "NA", "0", "NA", "0", "NA", "NA", "NA", "0", "NA", "NA", "0", "0", "NA", "NA", "NA", "0", "NA", "NA", "NA", "NA", "1", "7", "0", "NA", "NA", "6"], ["480715", "Pedro Obiang (West Ham United) wins a free kick in the defensive half.", "6'", "AFC Bournemouth", "0", "0", "0", "0", "0", "0", "NA", "NA", "NA", "NA", "NA", "NA", "NA", "0", "NA", "NA", "0", "NA", "0", "0", "NA", "NA", "NA", "0", "NA", "NA", "NA", "0", "NA", "NA", "0", "NA", "1", "Pedro Obiang", "West Ham United", "defensive half", "0", "NA", "NA", "0", "0", "NA", "NA", "NA", "0", "NA", "NA", "NA", "NA", "1", "8", "0", "NA", "NA", "6"], ["480715", "Corner,  West Ham United. Conceded by Adam Smith.", "7'", "AFC Bournemouth", "0", "0", "0", "0", "0", "0", "NA", "NA", "NA", "NA", "NA", "NA", "NA", "0", "NA", "NA", "0", "NA", "0", "0", "NA", "NA", "NA", "0", "NA", "NA", "NA", "0", "NA", "NA", "0", "NA", "0", "NA", "NA", "NA", "1", "West Ham United", "Adam Smith", "0", "0", "NA", "NA", "NA", "0", "NA", "NA", "NA", "NA", "1", "9", "0", "NA", "NA", "7"], ["480715", "Goal!  Bournemouth 0, West Ham United 1. James Collins (West Ham United) header from the right side of the six yard box to the bottom right corner. Assisted by Aaron Cresswell with a cross following a corner.", "7'", "AFC Bournemouth", "0", "0", "0", "0", "1", "0", "goal", "James Collins", "West Ham United", "header", "the right side of the six yard box", "bottom right corner", "Aaron Cresswell", "0", "NA", "NA", "0", "cross", "1", "0", "NA", "NA", "NA", "0", "NA", "NA", "NA", "0", "NA", "NA", "0", "NA", "0", "NA", "NA", "NA", "0", "NA", "NA", "0", "0", "NA", "NA", "NA", "0", "NA", "NA", "NA", "NA", "1", "10", "0", "NA", "NA", "7"], ["480715", "Foul by Arthur Masuaku (West Ham United).", "9'", "AFC Bournemouth", "0", "0", "0", "0", "0", "0", "NA", "NA", "NA", "NA", "NA", "NA", "NA", "1", "Arthur Masuaku", "West Ham United", "0", "NA", "0", "0", "NA", "NA", "NA", "0", "NA", "NA", "NA", "0", "NA", "NA", "0", "NA", "0", "NA", "NA", "NA", "0", "NA", "NA", "0", "0", "NA", "NA", "NA", "0", "NA", "NA", "NA", "NA", "1", "11", "0", "NA", "NA", "9"], ["480715", "Simon Francis (Bournemouth) wins a free kick in the defensive half.", "9'", "AFC Bournemouth", "0", "0", "0", "0", "0", "0", "NA", "NA", "NA", "NA", "NA", "NA", "NA", "0", "NA", "NA", "0", "NA", "0", "0", "NA", "NA", "NA", "0", "NA", "NA", "NA", "0", "NA", "NA", "0", "NA", "1", "Simon Francis", "Bournemouth", "defensive half", "0", "NA", "NA", "0", "0", "NA", "NA", "NA", "0", "NA", "NA", "NA", "NA", "1", "12", "0", "NA", "NA", "9"], ["480715", "Cheikhou Kouyaté (West Ham United) wins a free kick in the defensive half.", "11'", "AFC Bournemouth", "0", "0", "0", "0", "0", "0", "NA", "NA", "NA", "NA", "NA", "NA", "NA", "0", "NA", "NA", "0", "NA", "0", "0", "NA", "NA", "NA", "0", "NA", "NA", "NA", "0", "NA", "NA", "0", "NA", "1", "Cheikhou Kouyaté", "West Ham United", "defensive half", "0", "NA", "NA", "0", "0", "NA", "NA", "NA", "0", "NA", "NA", "NA", "NA", "1", "13", "0", "NA", "NA", "11"], ["480715", "Foul by Callum Wilson (Bournemouth).", "11'", "AFC Bournemouth", "0", "0", "0", "0", "0", "0", "NA", "NA", "NA", "NA", "NA", "NA", "NA", "1", "Callum Wilson", "Bournemouth", "0", "NA", "0", "0", "NA", "NA", "NA", "0", "NA", "NA", "NA", "0", "NA", "NA", "0", "NA", "0", "NA", "NA", "NA", "0", "NA", "NA", "0", "0", "NA", "NA", "NA", "0", "NA", "NA", "NA", "NA", "1", "14", "0", "NA", "NA", "11"], ["480715", "Foul by Pedro Obiang (West Ham United).", "13'", "AFC Bournemouth", "0", "0", "0", "0", "0", "0", "NA", "NA", "NA", "NA", "NA", "NA", "NA", "1", "Pedro Obiang", "West Ham United", "0", "NA", "0", "0", "NA", "NA", "NA", "0", "NA", "NA", "NA", "0", "NA", "NA", "0", "NA", "0", "NA", "NA", "NA", "0", "NA", "NA", "0", "0", "NA", "NA", "NA", "0", "NA", "NA", "NA", "NA", "1", "15", "0", "NA", "NA", "13"], ["480715", "Joshua King (Bournemouth) wins a free kick in the attacking half.", "13'", "AFC Bournemouth", "0", "0", "0", "0", "0", "0", "NA", "NA", "NA", "NA", "NA", "NA", "NA", "0", "NA", "NA", "0", "NA", "0", "0", "NA", "NA", "NA", "0", "NA", "NA", "NA", "0", "NA", "NA", "0", "NA", "1", "Joshua King", "Bournemouth", "attacking half", "0", "NA", "NA", "0", "0", "NA", "NA", "NA", "0", "NA", "NA", "NA", "NA", "1", "16", "0", "NA", "NA", "13"], ["480715", "Foul by Pablo Zabaleta (West Ham United).", "13'", "AFC Bournemouth", "0", "0", "0", "0", "0", "0", "NA", "NA", "NA", "NA", "NA", "NA", "NA", "1", "Pablo Zabaleta", "West Ham United", "0", "NA", "0", "0", "NA", "NA", "NA", "0", "NA", "NA", "NA", "0", "NA", "NA", "0", "NA", "0", "NA", "NA", "NA", "0", "NA", "NA", "0", "0", "NA", "NA", "NA", "0", "NA", "NA", "NA", "NA", "1", "17", "0", "NA", "NA", "13"], ["480715", "Ryan Fraser (Bournemouth) wins a free kick on the left wing.", "13'", "AFC Bournemouth", "0", "0", "0", "0", "0", "0", "NA", "NA", "NA", "NA", "NA", "NA", "NA", "0", "NA", "NA", "0", "NA", "0", "0", "NA", "NA", "NA", "0", "NA", "NA", "NA", "0", "NA", "NA", "0", "NA", "1", "Ryan Fraser", "Bournemouth", "NA", "0", "NA", "NA", "0", "0", "NA", "NA", "NA", "0", "NA", "NA", "NA", "NA", "1", "18", "0", "NA", "NA", "13"], ["480715", "Attempt missed. Joshua King (Bournemouth) left footed shot from the centre of the box misses to the left. Assisted by Callum Wilson with a cross.", "16'", "AFC Bournemouth", "0", "0", "0", "0", "1", "0", "missed", "Joshua King", "Bournemouth", "left", "the centre of the box", "left", "Callum Wilson", "0", "NA", "NA", "0", "cross", "0", "0", "NA", "NA", "NA", "0", "NA", "NA", "NA", "0", "NA", "NA", "0", "NA", "0", "NA", "NA", "NA", "0", "NA", "NA", "0", "0", "NA", "NA", "NA", "0", "NA", "NA", "NA", "NA", "1", "19", "0", "NA", "NA", "16"], ["480715", "Corner,  West Ham United. Conceded by Nathan Aké.", "17'", "AFC Bournemouth", "0", "0", "0", "0", "0", "0", "NA", "NA", "NA", "NA", "NA", "NA", "NA", "0", "NA", "NA", "0", "NA", "0", "0", "NA", "NA", "NA", "0", "NA", "NA", "NA", "0", "NA", "NA", "0", "NA", "0", "NA", "NA", "NA", "1", "West Ham United", "Nathan Aké", "0", "0", "NA", "NA", "NA", "0", "NA", "NA", "NA", "NA", "1", "20", "0", "NA", "NA", "17"], ["480715", "Attempt missed. André Ayew (West Ham United) left footed shot from the centre of the box is close, but misses to the left. Assisted by Arthur Masuaku with a cross.", "20'", "AFC Bournemouth", "0", "0", "0", "0", "1", "0", "missed", "André Ayew", "West Ham United", "left", "the centre of the box", "close, but left", "Arthur Masuaku", "0", "NA", "NA", "0", "cross", "0", "0", "NA", "NA", "NA", "0", "NA", "NA", "NA", "0", "NA", "NA", "0", "NA", "0", "NA", "NA", "NA", "0", "NA", "NA", "0", "0", "NA", "NA", "NA", "0", "NA", "NA", "NA", "NA", "1", "21", "0", "NA", "NA", "20"], ["480715", "Attempt missed. Joshua King (Bournemouth) right footed shot from the centre of the box is close, but misses to the right. Assisted by Ryan Fraser.", "22'", "AFC Bournemouth", "0", "0", "0", "0", "1", "0", "missed", "Joshua King", "Bournemouth", "right", "the centre of the box", "close, but right", "Ryan Fraser", "0", "NA", "NA", "0", "NA", "0", "0", "NA", "NA", "NA", "0", "NA", "NA", "NA", "0", "NA", "NA", "0", "NA", "0", "NA", "NA", "NA", "0", "NA", "NA", "0", "0", "NA", "NA", "NA", "0", "NA", "NA", "NA", "NA", "1", "22", "0", "NA", "NA", "22"], ["480715", "Attempt blocked. Jordon Ibe (Bournemouth) right footed shot from the centre of the box is blocked.", "23'", "AFC Bournemouth", "0", "0", "0", "0", "1", "0", "blocked", "Jordon Ibe", "Bournemouth", "right", "the centre of the box", "NA", "NA", "0", "NA", "NA", "0", "NA", "0", "0", "NA", "NA", "NA", "0", "NA", "NA", "NA", "0", "NA", "NA", "0", "NA", "0", "NA", "NA", "NA", "0", "NA", "NA", "0", "0", "NA", "NA", "NA", "0", "NA", "NA", "NA", "NA", "1", "23", "0", "NA", "NA", "23"], ["480715", "Attempt saved. Adam Smith (Bournemouth) right footed shot from outside the box is saved in the top centre of the goal.", "23'", "AFC Bournemouth", "0", "0", "0", "0", "1", "0", "saved", "Adam Smith", "Bournemouth", "right", "outside the box", "the top centre of the goal", "NA", "0", "NA", "NA", "0", "NA", "0", "0", "NA", "NA", "NA", "0", "NA", "NA", "NA", "0", "NA", "NA", "0", "NA", "0", "NA", "NA", "NA", "0", "NA", "NA", "0", "0", "NA", "NA", "NA", "0", "NA", "NA", "NA", "NA", "1", "24", "0", "NA", "NA", "23"], ["480715", "Corner,  Bournemouth. Conceded by Adrián.", "23'", "AFC Bournemouth", "0", "0", "0", "0", "0", "0", "NA", "NA", "NA", "NA", "NA", "NA", "NA", "0", "NA", "NA", "0", "NA", "0", "0", "NA", "NA", "NA", "0", "NA", "NA", "NA", "0", "NA", "NA", "0", "NA", "0", "NA", "NA", "NA", "1", "Bournemouth", "Adrián", "0", "0", "NA", "NA", "NA", "0", "NA", "NA", "NA", "NA", "1", "25", "0", "NA", "NA", "23"], ["480715", "Aaron Cresswell (West Ham United) wins a free kick in the defensive half.", "25'", "AFC Bournemouth", "0", "0", "0", "0", "0", "0", "NA", "NA", "NA", "NA", "NA", "NA", "NA", "0", "NA", "NA", "0", "NA", "0", "0", "NA", "NA", "NA", "0", "NA", "NA", "NA", "0", "NA", "NA", "0", "NA", "1", "Aaron Cresswell", "West Ham United", "defensive half", "0", "NA", "NA", "0", "0", "NA", "NA", "NA", "0", "NA", "NA", "NA", "NA", "1", "26", "0", "NA", "NA", "25"], ["480715", "Foul by Callum Wilson (Bournemouth).", "25'", "AFC Bournemouth", "0", "0", "0", "0", "0", "0", "NA", "NA", "NA", "NA", "NA", "NA", "NA", "1", "Callum Wilson", "Bournemouth", "0", "NA", "0", "0", "NA", "NA", "NA", "0", "NA", "NA", "NA", "0", "NA", "NA", "0", "NA", "0", "NA", "NA", "NA", "0", "NA", "NA", "0", "0", "NA", "NA", "NA", "0", "NA", "NA", "NA", "NA", "1", "27", "0", "NA", "NA", "25"], ["480715", "Offside, West Ham United. Aaron Cresswell tries a through ball, but Marko Arnautovic is caught offside.", "25'", "AFC Bournemouth", "0", "0", "0", "0", "0", "0", "NA", "NA", "NA", "NA", "NA", "NA", "NA", "0", "NA", "NA", "0", "NA", "0", "1", "West Ham United", "Marko Arnautovic", "Aaron Cresswell", "0", "NA", "NA", "NA", "0", "NA", "NA", "0", "NA", "0", "NA", "NA", "NA", "0", "NA", "NA", "0", "0", "NA", "NA", "NA", "0", "NA", "NA", "NA", "NA", "1", "28", "0", "NA", "NA", "25"], ["480715", "Arthur Masuaku (West Ham United) wins a free kick in the defensive half.", "26'", "AFC Bournemouth", "0", "0", "0", "0", "0", "0", "NA", "NA", "NA", "NA", "NA", "NA", "NA", "0", "NA", "NA", "0", "NA", "0", "0", "NA", "NA", "NA", "0", "NA", "NA", "NA", "0", "NA", "NA", "0", "NA", "1", "Arthur Masuaku", "West Ham United", "defensive half", "0", "NA", "NA", "0", "0", "NA", "NA", "NA", "0", "NA", "NA", "NA", "NA", "1", "29", "0", "NA", "NA", "26"], ["480715", "Foul by Simon Francis (Bournemouth).", "26'", "AFC Bournemouth", "0", "0", "0", "0", "0", "0", "NA", "NA", "NA", "NA", "NA", "NA", "NA", "1", "Simon Francis", "Bournemouth", "0", "NA", "0", "0", "NA", "NA", "NA", "0", "NA", "NA", "NA", "0", "NA", "NA", "0", "NA", "0", "NA", "NA", "NA", "0", "NA", "NA", "0", "0", "NA", "NA", "NA", "0", "NA", "NA", "NA", "NA", "1", "30", "0", "NA", "NA", "26"], ["480715", "Offside, West Ham United. Aaron Cresswell tries a through ball, but Marko Arnautovic is caught offside.", "27'", "AFC Bournemouth", "0", "0", "0", "0", "0", "0", "NA", "NA", "NA", "NA", "NA", "NA", "NA", "0", "NA", "NA", "0", "NA", "0", "1", "West Ham United", "Marko Arnautovic", "Aaron Cresswell", "0", "NA", "NA", "NA", "0", "NA", "NA", "0", "NA", "0", "NA", "NA", "NA", "0", "NA", "NA", "0", "0", "NA", "NA", "NA", "0", "NA", "NA", "NA", "NA", "1", "31", "0", "NA", "NA", "27"], ["480715", "Foul by André Ayew (West Ham United).", "29'", "AFC Bournemouth", "0", "0", "0", "0", "0", "0", "NA", "NA", "NA", "NA", "NA", "NA", "NA", "1", "André Ayew", "West Ham United", "0", "NA", "0", "0", "NA", "NA", "NA", "0", "NA", "NA", "NA", "0", "NA", "NA", "0", "NA", "0", "NA", "NA", "NA", "0", "NA", "NA", "0", "0", "NA", "NA", "NA", "0", "NA", "NA", "NA", "NA", "1", "32", "0", "NA", "NA", "29"], ["480715", "Ryan Fraser (Bournemouth) wins a free kick in the attacking half.", "29'", "AFC Bournemouth", "0", "0", "0", "0", "0", "0", "NA", "NA", "NA", "NA", "NA", "NA", "NA", "0", "NA", "NA", "0", "NA", "0", "0", "NA", "NA", "NA", "0", "NA", "NA", "NA", "0", "NA", "NA", "0", "NA", "1", "Ryan Fraser", "Bournemouth", "attacking half", "0", "NA", "NA", "0", "0", "NA", "NA", "NA", "0", "NA", "NA", "NA", "NA", "1", "33", "0", "NA", "NA", "29"], ["480715", "Goal!  Bournemouth 1, West Ham United 1. Dan Gosling (Bournemouth) left footed shot from the centre of the box to the centre of the goal. Assisted by Joshua King following a set piece situation.", "29'", "AFC Bournemouth", "1", "0", "0", "0", "1", "0", "goal", "Dan Gosling", "Bournemouth", "left", "the centre of the box", "centre of the goal", "Joshua King", "0", "NA", "NA", "1", "NA", "0", "0", "NA", "NA", "NA", "0", "NA", "NA", "NA", "0", "NA", "NA", "0", "NA", "0", "NA", "NA", "NA", "0", "NA", "NA", "0", "0", "NA", "NA", "NA", "0", "NA", "NA", "NA", "NA", "1", "34", "0", "NA", "NA", "29"], ["480715", "Cheikhou Kouyaté (West Ham United) wins a free kick on the left wing.", "31'", "AFC Bournemouth", "1", "0", "0", "0", "0", "0", "NA", "NA", "NA", "NA", "NA", "NA", "NA", "0", "NA", "NA", "0", "NA", "0", "0", "NA", "NA", "NA", "0", "NA", "NA", "NA", "0", "NA", "NA", "0", "NA", "1", "Cheikhou Kouyaté", "West Ham United", "NA", "0", "NA", "NA", "0", "0", "NA", "NA", "NA", "0", "NA", "NA", "NA", "NA", "1", "35", "0", "NA", "NA", "31"], ["480715", "Foul by Simon Francis (Bournemouth).", "31'", "AFC Bournemouth", "1", "0", "0", "0", "0", "0", "NA", "NA", "NA", "NA", "NA", "NA", "NA", "1", "Simon Francis", "Bournemouth", "0", "NA", "0", "0", "NA", "NA", "NA", "0", "NA", "NA", "NA", "0", "NA", "NA", "0", "NA", "0", "NA", "NA", "NA", "0", "NA", "NA", "0", "0", "NA", "NA", "NA", "0", "NA", "NA", "NA", "NA", "1", "36", "0", "NA", "NA", "31"], ["480715", "Delay in match Cheikhou Kouyaté (West Ham United) because of an injury.", "31'", "AFC Bournemouth", "1", "0", "0", "0", "0", "0", "NA", "NA", "NA", "NA", "NA", "NA", "NA", "0", "NA", "NA", "0", "NA", "0", "0", "NA", "NA", "NA", "0", "NA", "NA", "NA", "0", "NA", "NA", "1", "West Ham United", "0", "NA", "NA", "NA", "0", "NA", "NA", "0", "0", "NA", "NA", "NA", "0", "NA", "NA", "NA", "NA", "1", "37", "0", "NA", "NA", "31"], ["480715", "Simon Francis (Bournemouth) is shown the yellow card for a bad foul.", "32'", "AFC Bournemouth", "1", "0", "0", "0", "0", "0", "NA", "NA", "NA", "NA", "NA", "NA", "NA", "0", "NA", "NA", "0", "NA", "0", "0", "NA", "NA", "NA", "1", "yellow", "Simon Francis", "Bournemouth", "0", "NA", "NA", "0", "NA", "0", "NA", "NA", "NA", "0", "NA", "NA", "0", "0", "NA", "NA", "NA", "0", "NA", "NA", "NA", "NA", "1", "38", "0", "NA", "NA", "32"], ["480715", "Delay over. They are ready to continue.", "35'", "AFC Bournemouth", "1", "0", "0", "0", "0", "0", "NA", "NA", "NA", "NA", "NA", "NA", "NA", "0", "NA", "NA", "0", "NA", "0", "0", "NA", "NA", "NA", "0", "NA", "NA", "NA", "0", "NA", "NA", "0", "NA", "0", "NA", "NA", "NA", "0", "NA", "NA", "0", "0", "NA", "NA", "NA", "0", "NA", "NA", "NA", "NA", "1", "39", "0", "NA", "NA", "35"], ["480715", "Adam Smith (Bournemouth) wins a free kick on the left wing.", "36'", "AFC Bournemouth", "1", "0", "0", "0", "0", "0", "NA", "NA", "NA", "NA", "NA", "NA", "NA", "0", "NA", "NA", "0", "NA", "0", "0", "NA", "NA", "NA", "0", "NA", "NA", "NA", "0", "NA", "NA", "0", "NA", "1", "Adam Smith", "Bournemouth", "NA", "0", "NA", "NA", "0", "0", "NA", "NA", "NA", "0", "NA", "NA", "NA", "NA", "1", "40", "0", "NA", "NA", "36"], ["480715", "Foul by Pablo Zabaleta (West Ham United).", "36'", "AFC Bournemouth", "1", "0", "0", "0", "0", "0", "NA", "NA", "NA", "NA", "NA", "NA", "NA", "1", "Pablo Zabaleta", "West Ham United", "0", "NA", "0", "0", "NA", "NA", "NA", "0", "NA", "NA", "NA", "0", "NA", "NA", "0", "NA", "0", "NA", "NA", "NA", "0", "NA", "NA", "0", "0", "NA", "NA", "NA", "0", "NA", "NA", "NA", "NA", "1", "41", "0", "NA", "NA", "36"], ["480715", "Pablo Zabaleta (West Ham United) is shown the yellow card.", "37'", "AFC Bournemouth", "1", "0", "0", "0", "0", "0", "NA", "NA", "NA", "NA", "NA", "NA", "NA", "0", "NA", "NA", "0", "NA", "0", "0", "NA", "NA", "NA", "1", "yellow", "Pablo Zabaleta", "West Ham United", "0", "NA", "NA", "0", "NA", "0", "NA", "NA", "NA", "0", "NA", "NA", "0", "0", "NA", "NA", "NA", "0", "NA", "NA", "NA", "NA", "1", "42", "0", "NA", "NA", "37"], ["480715", "Foul by Pedro Obiang (West Ham United).", "39'", "AFC Bournemouth", "1", "0", "0", "0", "0", "0", "NA", "NA", "NA", "NA", "NA", "NA", "NA", "1", "Pedro Obiang", "West Ham United", "0", "NA", "0", "0", "NA", "NA", "NA", "0", "NA", "NA", "NA", "0", "NA", "NA", "0", "NA", "0", "NA", "NA", "NA", "0", "NA", "NA", "0", "0", "NA", "NA", "NA", "0", "NA", "NA", "NA", "NA", "1", "43", "0", "NA", "NA", "39"], ["480715", "Jordon Ibe (Bournemouth) wins a free kick in the attacking half.", "39'", "AFC Bournemouth", "1", "0", "0", "0", "0", "0", "NA", "NA", "NA", "NA", "NA", "NA", "NA", "0", "NA", "NA", "0", "NA", "0", "0", "NA", "NA", "NA", "0", "NA", "NA", "NA", "0", "NA", "NA", "0", "NA", "1", "Jordon Ibe", "Bournemouth", "attacking half", "0", "NA", "NA", "0", "0", "NA", "NA", "NA", "0", "NA", "NA", "NA", "NA", "1", "44", "0", "NA", "NA", "39"], ["480715", "Attempt blocked. Ryan Fraser (Bournemouth) left footed shot from outside the box is blocked. Assisted by Jordon Ibe.", "40'", "AFC Bournemouth", "1", "0", "0", "0", "1", "0", "blocked", "Ryan Fraser", "Bournemouth", "left", "outside the box", "NA", "Jordon Ibe", "0", "NA", "NA", "0", "NA", "0", "0", "NA", "NA", "NA", "0", "NA", "NA", "NA", "0", "NA", "NA", "0", "NA", "0", "NA", "NA", "NA", "0", "NA", "NA", "0", "0", "NA", "NA", "NA", "0", "NA", "NA", "NA", "NA", "1", "45", "0", "NA", "NA", "40"], ["480715", "André Ayew (West Ham United) wins a free kick in the defensive half.", "41'", "AFC Bournemouth", "1", "0", "0", "0", "0", "0", "NA", "NA", "NA", "NA", "NA", "NA", "NA", "0", "NA", "NA", "0", "NA", "0", "0", "NA", "NA", "NA", "0", "NA", "NA", "NA", "0", "NA", "NA", "0", "NA", "1", "André Ayew", "West Ham United", "defensive half", "0", "NA", "NA", "0", "0", "NA", "NA", "NA", "0", "NA", "NA", "NA", "NA", "1", "46", "0", "NA", "NA", "41"], ["480715", "Foul by Adam Smith (Bournemouth).", "41'", "AFC Bournemouth", "1", "0", "0", "0", "0", "0", "NA", "NA", "NA", "NA", "NA", "NA", "NA", "1", "Adam Smith", "Bournemouth", "0", "NA", "0", "0", "NA", "NA", "NA", "0", "NA", "NA", "NA", "0", "NA", "NA", "0", "NA", "0", "NA", "NA", "NA", "0", "NA", "NA", "0", "0", "NA", "NA", "NA", "0", "NA", "NA", "NA", "NA", "1", "47", "0", "NA", "NA", "41"], ["480715", "Attempt missed. Manuel Lanzini (West Ham United) right footed shot from the centre of the box misses to the right. Assisted by Marko Arnautovic.", "44'", "AFC Bournemouth", "1", "0", "0", "0", "1", "0", "missed", "Manuel Lanzini", "West Ham United", "right", "the centre of the box", "right", "Marko Arnautovic", "0", "NA", "NA", "0", "NA", "0", "0", "NA", "NA", "NA", "0", "NA", "NA", "NA", "0", "NA", "NA", "0", "NA", "0", "NA", "NA", "NA", "0", "NA", "NA", "0", "0", "NA", "NA", "NA", "0", "NA", "NA", "NA", "NA", "1", "48", "0", "NA", "NA", "44"], ["480715", "Foul by Marko Arnautovic (West Ham United).", "45'+2'", "AFC Bournemouth", "1", "0", "0", "0", "0", "0", "NA", "NA", "NA", "NA", "NA", "NA", "NA", "1", "Marko Arnautovic", "West Ham United", "0", "NA", "0", "0", "NA", "NA", "NA", "0", "NA", "NA", "NA", "0", "NA", "NA", "0", "NA", "0", "NA", "NA", "NA", "0", "NA", "NA", "0", "0", "NA", "NA", "NA", "0", "NA", "NA", "NA", "NA", "1", "49", "1", "NA", "NA", "47"], ["480715", "Steve Cook (Bournemouth) wins a free kick on the right wing.", "45'+2'", "AFC Bournemouth", "1", "0", "0", "0", "0", "0", "NA", "NA", "NA", "NA", "NA", "NA", "NA", "0", "NA", "NA", "0", "NA", "0", "0", "NA", "NA", "NA", "0", "NA", "NA", "NA", "0", "NA", "NA", "0", "NA", "1", "Steve Cook", "Bournemouth", "NA", "0", "NA", "NA", "0", "0", "NA", "NA", "NA", "0", "NA", "NA", "NA", "NA", "1", "50", "1", "NA", "NA", "47"], ["480715", "Attempt missed. Joshua King (Bournemouth) header from the centre of the box misses to the left. Assisted by Jordon Ibe with a cross following a set piece situation.", "45'+2'", "AFC Bournemouth", "1", "0", "0", "0", "1", "0", "missed", "Joshua King", "Bournemouth", "header", "the centre of the box", "left", "Jordon Ibe", "0", "NA", "NA", "1", "cross", "0", "0", "NA", "NA", "NA", "0", "NA", "NA", "NA", "0", "NA", "NA", "0", "NA", "0", "NA", "NA", "NA", "0", "NA", "NA", "0", "0", "NA", "NA", "NA", "0", "NA", "NA", "NA", "NA", "1", "51", "1", "NA", "NA", "47"], ["480715", "Attempt blocked. Nathan Aké (Bournemouth) header from the centre of the box is blocked. Assisted by Ryan Fraser with a cross.", "45'+2'", "AFC Bournemouth", "1", "0", "0", "0", "1", "0", "blocked", "Nathan Aké", "Bournemouth", "header", "the centre of the box", "NA", "Ryan Fraser", "0", "NA", "NA", "0", "cross", "0", "0", "NA", "NA", "NA", "0", "NA", "NA", "NA", "0", "NA", "NA", "0", "NA", "0", "NA", "NA", "NA", "0", "NA", "NA", "0", "0", "NA", "NA", "NA", "0", "NA", "NA", "NA", "NA", "1", "52", "1", "NA", "NA", "47"], ["480715", "Attempt blocked. Dan Gosling (Bournemouth) right footed shot from the centre of the box is blocked. Assisted by Simon Francis.", "45'+2'", "AFC Bournemouth", "1", "0", "0", "0", "1", "0", "blocked", "Dan Gosling", "Bournemouth", "right", "the centre of the box", "NA", "Simon Francis", "0", "NA", "NA", "0", "NA", "0", "0", "NA", "NA", "NA", "0", "NA", "NA", "NA", "0", "NA", "NA", "0", "NA", "0", "NA", "NA", "NA", "0", "NA", "NA", "0", "0", "NA", "NA", "NA", "0", "NA", "NA", "NA", "NA", "1", "53", "1", "NA", "NA", "47"], ["480715", "Attempt saved. Joshua King (Bournemouth) header from the centre of the box is saved in the centre of the goal.", "45'+3'", "AFC Bournemouth", "1", "0", "0", "0", "1", "0", "saved", "Joshua King", "Bournemouth", "header", "the centre of the box", "the centre of the goal", "NA", "0", "NA", "NA", "0", "NA", "0", "0", "NA", "NA", "NA", "0", "NA", "NA", "NA", "0", "NA", "NA", "0", "NA", "0", "NA", "NA", "NA", "0", "NA", "NA", "0", "0", "NA", "NA", "NA", "0", "NA", "NA", "NA", "NA", "1", "54", "1", "NA", "NA", "48"], ["480715", "Attempt missed. Steve Cook (Bournemouth) right footed shot from outside the box is high and wide to the right. Assisted by Nathan Aké.", "45'+3'", "AFC Bournemouth", "1", "0", "0", "0", "1", "0", "missed", "Steve Cook", "Bournemouth", "right", "outside the box", "high and wide to the right", "Nathan Aké", "0", "NA", "NA", "0", "NA", "0", "0", "NA", "NA", "NA", "0", "NA", "NA", "NA", "0", "NA", "NA", "0", "NA", "0", "NA", "NA", "NA", "0", "NA", "NA", "0", "0", "NA", "NA", "NA", "0", "NA", "NA", "NA", "NA", "1", "55", "1", "NA", "NA", "48"], ["480715", "Attempt blocked. Arthur Masuaku (West Ham United) left footed shot from the left side of the box is blocked. Assisted by Marko Arnautovic.", "45'+4'", "AFC Bournemouth", "1", "0", "0", "0", "1", "0", "blocked", "Arthur Masuaku", "West Ham United", "left", "the left side of the box", "NA", "Marko Arnautovic", "0", "NA", "NA", "0", "NA", "0", "0", "NA", "NA", "NA", "0", "NA", "NA", "NA", "0", "NA", "NA", "0", "NA", "0", "NA", "NA", "NA", "0", "NA", "NA", "0", "0", "NA", "NA", "NA", "0", "NA", "NA", "NA", "NA", "1", "56", "1", "NA", "NA", "49"], ["480715", "First Half ends, Bournemouth 1, West Ham United 1.", "45'+5'", "AFC Bournemouth", "1", "1", "0", "0", "0", "0", "NA", "NA", "NA", "NA", "NA", "NA", "NA", "0", "NA", "NA", "0", "NA", "0", "0", "NA", "NA", "NA", "0", "NA", "NA", "NA", "0", "NA", "NA", "0", "NA", "0", "NA", "NA", "NA", "0", "NA", "NA", "0", "0", "NA", "NA", "NA", "0", "NA", "NA", "NA", "NA", "1", "57", "1", "NA", "NA", "50"], ["480715", "Second Half begins Bournemouth 1, West Ham United 1.", "45'", "AFC Bournemouth", "1", "0", "0", "1", "0", "0", "NA", "NA", "NA", "NA", "NA", "NA", "NA", "0", "NA", "NA", "0", "NA", "0", "0", "NA", "NA", "NA", "0", "NA", "NA", "NA", "0", "NA", "NA", "0", "NA", "0", "NA", "NA", "NA", "0", "NA", "NA", "0", "0", "NA", "NA", "NA", "0", "NA", "NA", "NA", "NA", "2", "58", "0", "NA", "NA", "45"], ["480715", "Foul by Lewis Cook (Bournemouth).", "47'", "AFC Bournemouth", "1", "0", "0", "0", "0", "0", "NA", "NA", "NA", "NA", "NA", "NA", "NA", "1", "Lewis Cook", "Bournemouth", "0", "NA", "0", "0", "NA", "NA", "NA", "0", "NA", "NA", "NA", "0", "NA", "NA", "0", "NA", "0", "NA", "NA", "NA", "0", "NA", "NA", "0", "0", "NA", "NA", "NA", "0", "NA", "NA", "NA", "NA", "2", "59", "0", "NA", "NA", "47"], ["480715", "Pablo Zabaleta (West Ham United) wins a free kick in the defensive half.", "47'", "AFC Bournemouth", "1", "0", "0", "0", "0", "0", "NA", "NA", "NA", "NA", "NA", "NA", "NA", "0", "NA", "NA", "0", "NA", "0", "0", "NA", "NA", "NA", "0", "NA", "NA", "NA", "0", "NA", "NA", "0", "NA", "1", "Pablo Zabaleta", "West Ham United", "defensive half", "0", "NA", "NA", "0", "0", "NA", "NA", "NA", "0", "NA", "NA", "NA", "NA", "2", "60", "0", "NA", "NA", "47"], ["480715", "Attempt missed. Callum Wilson (Bournemouth) right footed shot from outside the box misses to the left. Assisted by Joshua King.", "51'", "AFC Bournemouth", "1", "0", "0", "0", "1", "0", "missed", "Callum Wilson", "Bournemouth", "right", "outside the box", "left", "Joshua King", "0", "NA", "NA", "0", "NA", "0", "0", "NA", "NA", "NA", "0", "NA", "NA", "NA", "0", "NA", "NA", "0", "NA", "0", "NA", "NA", "NA", "0", "NA", "NA", "0", "0", "NA", "NA", "NA", "0", "NA", "NA", "NA", "NA", "2", "61", "0", "NA", "NA", "51"], ["480715", "Corner,  West Ham United. Conceded by Joshua King.", "52'", "AFC Bournemouth", "1", "0", "0", "0", "0", "0", "NA", "NA", "NA", "NA", "NA", "NA", "NA", "0", "NA", "NA", "0", "NA", "0", "0", "NA", "NA", "NA", "0", "NA", "NA", "NA", "0", "NA", "NA", "0", "NA", "0", "NA", "NA", "NA", "1", "West Ham United", "Joshua King", "0", "0", "NA", "NA", "NA", "0", "NA", "NA", "NA", "NA", "2", "62", "0", "NA", "NA", "52"], ["480715", "Attempt blocked. Manuel Lanzini (West Ham United) left footed shot from the left side of the box is blocked. Assisted by Marko Arnautovic.", "54'", "AFC Bournemouth", "1", "0", "0", "0", "1", "0", "blocked", "Manuel Lanzini", "West Ham United", "left", "the left side of the box", "NA", "Marko Arnautovic", "0", "NA", "NA", "0", "NA", "0", "0", "NA", "NA", "NA", "0", "NA", "NA", "NA", "0", "NA", "NA", "0", "NA", "0", "NA", "NA", "NA", "0", "NA", "NA", "0", "0", "NA", "NA", "NA", "0", "NA", "NA", "NA", "NA", "2", "63", "0", "NA", "NA", "54"], ["480715", "Corner,  West Ham United. Conceded by Lewis Cook.", "54'", "AFC Bournemouth", "1", "0", "0", "0", "0", "0", "NA", "NA", "NA", "NA", "NA", "NA", "NA", "0", "NA", "NA", "0", "NA", "0", "0", "NA", "NA", "NA", "0", "NA", "NA", "NA", "0", "NA", "NA", "0", "NA", "0", "NA", "NA", "NA", "1", "West Ham United", "Lewis Cook", "0", "0", "NA", "NA", "NA", "0", "NA", "NA", "NA", "NA", "2", "64", "0", "NA", "NA", "54"], ["480715", "Dan Gosling (Bournemouth) wins a free kick in the defensive half.", "55'", "AFC Bournemouth", "1", "0", "0", "0", "0", "0", "NA", "NA", "NA", "NA", "NA", "NA", "NA", "0", "NA", "NA", "0", "NA", "0", "0", "NA", "NA", "NA", "0", "NA", "NA", "NA", "0", "NA", "NA", "0", "NA", "1", "Dan Gosling", "Bournemouth", "defensive half", "0", "NA", "NA", "0", "0", "NA", "NA", "NA", "0", "NA", "NA", "NA", "NA", "2", "65", "0", "NA", "NA", "55"], ["480715", "Foul by James Collins (West Ham United).", "55'", "AFC Bournemouth", "1", "0", "0", "0", "0", "0", "NA", "NA", "NA", "NA", "NA", "NA", "NA", "1", "James Collins", "West Ham United", "0", "NA", "0", "0", "NA", "NA", "NA", "0", "NA", "NA", "NA", "0", "NA", "NA", "0", "NA", "0", "NA", "NA", "NA", "0", "NA", "NA", "0", "0", "NA", "NA", "NA", "0", "NA", "NA", "NA", "NA", "2", "66", "0", "NA", "NA", "55"], ["480715", "James Collins (West Ham United) is shown the yellow card for a bad foul.", "55'", "AFC Bournemouth", "1", "0", "0", "0", "0", "0", "NA", "NA", "NA", "NA", "NA", "NA", "NA", "0", "NA", "NA", "0", "NA", "0", "0", "NA", "NA", "NA", "1", "yellow", "James Collins", "West Ham United", "0", "NA", "NA", "0", "NA", "0", "NA", "NA", "NA", "0", "NA", "NA", "0", "0", "NA", "NA", "NA", "0", "NA", "NA", "NA", "NA", "2", "67", "0", "NA", "NA", "55"], ["480715", "Callum Wilson (Bournemouth) wins a free kick on the right wing.", "56'", "AFC Bournemouth", "1", "0", "0", "0", "0", "0", "NA", "NA", "NA", "NA", "NA", "NA", "NA", "0", "NA", "NA", "0", "NA", "0", "0", "NA", "NA", "NA", "0", "NA", "NA", "NA", "0", "NA", "NA", "0", "NA", "1", "Callum Wilson", "Bournemouth", "NA", "0", "NA", "NA", "0", "0", "NA", "NA", "NA", "0", "NA", "NA", "NA", "NA", "2", "68", "0", "NA", "NA", "56"], ["480715", "Foul by Aaron Cresswell (West Ham United).", "56'", "AFC Bournemouth", "1", "0", "0", "0", "0", "0", "NA", "NA", "NA", "NA", "NA", "NA", "NA", "1", "Aaron Cresswell", "West Ham United", "0", "NA", "0", "0", "NA", "NA", "NA", "0", "NA", "NA", "NA", "0", "NA", "NA", "0", "NA", "0", "NA", "NA", "NA", "0", "NA", "NA", "0", "0", "NA", "NA", "NA", "0", "NA", "NA", "NA", "NA", "2", "69", "0", "NA", "NA", "56"], ["480715", "Aaron Cresswell (West Ham United) is shown the yellow card for a bad foul.", "56'", "AFC Bournemouth", "1", "0", "0", "0", "0", "0", "NA", "NA", "NA", "NA", "NA", "NA", "NA", "0", "NA", "NA", "0", "NA", "0", "0", "NA", "NA", "NA", "1", "yellow", "Aaron Cresswell", "West Ham United", "0", "NA", "NA", "0", "NA", "0", "NA", "NA", "NA", "0", "NA", "NA", "0", "0", "NA", "NA", "NA", "0", "NA", "NA", "NA", "NA", "2", "70", "0", "NA", "NA", "56"], ["480715", "Attempt blocked. Callum Wilson (Bournemouth) header from the left side of the box is blocked. Assisted by Jordon Ibe with a cross.", "57'", "AFC Bournemouth", "1", "0", "0", "0", "1", "0", "blocked", "Callum Wilson", "Bournemouth", "header", "the left side of the box", "NA", "Jordon Ibe", "0", "NA", "NA", "0", "cross", "0", "0", "NA", "NA", "NA", "0", "NA", "NA", "NA", "0", "NA", "NA", "0", "NA", "0", "NA", "NA", "NA", "0", "NA", "NA", "0", "0", "NA", "NA", "NA", "0", "NA", "NA", "NA", "NA", "2", "71", "0", "NA", "NA", "57"], ["480715", "Corner,  Bournemouth. Conceded by Pedro Obiang.", "57'", "AFC Bournemouth", "1", "0", "0", "0", "0", "0", "NA", "NA", "NA", "NA", "NA", "NA", "NA", "0", "NA", "NA", "0", "NA", "0", "0", "NA", "NA", "NA", "0", "NA", "NA", "NA", "0", "NA", "NA", "0", "NA", "0", "NA", "NA", "NA", "1", "Bournemouth", "Pedro Obiang", "0", "0", "NA", "NA", "NA", "0", "NA", "NA", "NA", "NA", "2", "72", "0", "NA", "NA", "57"], ["480715", "Goal!  Bournemouth 2, West Ham United 1. Nathan Aké (Bournemouth) left footed shot from the centre of the box to the bottom left corner. Assisted by Dan Gosling following a corner.", "57'", "AFC Bournemouth", "2", "0", "0", "0", "1", "0", "goal", "Nathan Aké", "Bournemouth", "left", "the centre of the box", "bottom left corner", "Dan Gosling", "0", "NA", "NA", "0", "NA", "1", "0", "NA", "NA", "NA", "0", "NA", "NA", "NA", "0", "NA", "NA", "0", "NA", "0", "NA", "NA", "NA", "0", "NA", "NA", "0", "0", "NA", "NA", "NA", "0", "NA", "NA", "NA", "NA", "2", "73", "0", "NA", "NA", "57"], ["480715", "Substitution, West Ham United. Andy Carroll replaces Pedro Obiang.", "60'", "AFC Bournemouth", "2", "0", "0", "0", "0", "0", "NA", "NA", "NA", "NA", "NA", "NA", "NA", "0", "NA", "NA", "0", "NA", "0", "0", "NA", "NA", "NA", "0", "NA", "NA", "NA", "0", "NA", "NA", "0", "NA", "0", "NA", "NA", "NA", "0", "NA", "NA", "1", "0", "West Ham United", "Andy Carroll", "Pedro Obiang", "0", "NA", "NA", "NA", "NA", "2", "74", "0", "NA", "NA", "60"], ["480715", "Substitution, West Ham United. Chicharito replaces André Ayew.", "61'", "AFC Bournemouth", "2", "0", "0", "0", "0", "0", "NA", "NA", "NA", "NA", "NA", "NA", "NA", "0", "NA", "NA", "0", "NA", "0", "0", "NA", "NA", "NA", "0", "NA", "NA", "NA", "0", "NA", "NA", "0", "NA", "0", "NA", "NA", "NA", "0", "NA", "NA", "1", "0", "West Ham United", "Chicharito", "André Ayew", "0", "NA", "NA", "NA", "NA", "2", "75", "0", "NA", "NA", "61"], ["480715", "Foul by Ryan Fraser (Bournemouth).", "61'", "AFC Bournemouth", "2", "0", "0", "0", "0", "0", "NA", "NA", "NA", "NA", "NA", "NA", "NA", "1", "Ryan Fraser", "Bournemouth", "0", "NA", "0", "0", "NA", "NA", "NA", "0", "NA", "NA", "NA", "0", "NA", "NA", "0", "NA", "0", "NA", "NA", "NA", "0", "NA", "NA", "0", "0", "NA", "NA", "NA", "0", "NA", "NA", "NA", "NA", "2", "76", "0", "NA", "NA", "61"], ["480715", "Pablo Zabaleta (West Ham United) wins a free kick on the right wing.", "61'", "AFC Bournemouth", "2", "0", "0", "0", "0", "0", "NA", "NA", "NA", "NA", "NA", "NA", "NA", "0", "NA", "NA", "0", "NA", "0", "0", "NA", "NA", "NA", "0", "NA", "NA", "NA", "0", "NA", "NA", "0", "NA", "1", "Pablo Zabaleta", "West Ham United", "NA", "0", "NA", "NA", "0", "0", "NA", "NA", "NA", "0", "NA", "NA", "NA", "NA", "2", "77", "0", "NA", "NA", "61"], ["480715", "Attempt saved. Dan Gosling (Bournemouth) right footed shot from the right side of the box is saved in the bottom right corner. Assisted by Lewis Cook.", "63'", "AFC Bournemouth", "2", "0", "0", "0", "1", "0", "saved", "Dan Gosling", "Bournemouth", "right", "the right side of the box", "the bottom right corner", "Lewis Cook", "0", "NA", "NA", "0", "NA", "0", "0", "NA", "NA", "NA", "0", "NA", "NA", "NA", "0", "NA", "NA", "0", "NA", "0", "NA", "NA", "NA", "0", "NA", "NA", "0", "0", "NA", "NA", "NA", "0", "NA", "NA", "NA", "NA", "2", "78", "0", "NA", "NA", "63"], ["480715", "Corner,  Bournemouth. Conceded by Adrián.", "63'", "AFC Bournemouth", "2", "0", "0", "0", "0", "0", "NA", "NA", "NA", "NA", "NA", "NA", "NA", "0", "NA", "NA", "0", "NA", "0", "0", "NA", "NA", "NA", "0", "NA", "NA", "NA", "0", "NA", "NA", "0", "NA", "0", "NA", "NA", "NA", "1", "Bournemouth", "Adrián", "0", "0", "NA", "NA", "NA", "0", "NA", "NA", "NA", "NA", "2", "79", "0", "NA", "NA", "63"], ["480715", "Corner,  Bournemouth. Conceded by Cheikhou Kouyaté.", "64'", "AFC Bournemouth", "2", "0", "0", "0", "0", "0", "NA", "NA", "NA", "NA", "NA", "NA", "NA", "0", "NA", "NA", "0", "NA", "0", "0", "NA", "NA", "NA", "0", "NA", "NA", "NA", "0", "NA", "NA", "0", "NA", "0", "NA", "NA", "NA", "1", "Bournemouth", "Cheikhou Kouyaté", "0", "0", "NA", "NA", "NA", "0", "NA", "NA", "NA", "NA", "2", "80", "0", "NA", "NA", "64"], ["480715", "Attempt missed. Nathan Aké (Bournemouth) header from the centre of the box is close, but misses to the right. Assisted by Jordon Ibe with a cross following a corner.", "64'", "AFC Bournemouth", "2", "0", "0", "0", "1", "0", "missed", "Nathan Aké", "Bournemouth", "header", "the centre of the box", "close, but right", "Jordon Ibe", "0", "NA", "NA", "0", "cross", "1", "0", "NA", "NA", "NA", "0", "NA", "NA", "NA", "0", "NA", "NA", "0", "NA", "0", "NA", "NA", "NA", "0", "NA", "NA", "0", "0", "NA", "NA", "NA", "0", "NA", "NA", "NA", "NA", "2", "81", "0", "NA", "NA", "64"], ["480715", "Substitution, Bournemouth. Benik Afobe replaces Joshua King.", "65'", "AFC Bournemouth", "2", "0", "0", "0", "0", "0", "NA", "NA", "NA", "NA", "NA", "NA", "NA", "0", "NA", "NA", "0", "NA", "0", "0", "NA", "NA", "NA", "0", "NA", "NA", "NA", "0", "NA", "NA", "0", "NA", "0", "NA", "NA", "NA", "0", "NA", "NA", "1", "0", "Bournemouth", "Benik Afobe", "Joshua King", "0", "NA", "NA", "NA", "NA", "2", "82", "0", "NA", "NA", "65"], ["480715", "Attempt saved. Jordon Ibe (Bournemouth) right footed shot from the right side of the box is saved in the centre of the goal. Assisted by Simon Francis.", "67'", "AFC Bournemouth", "2", "0", "0", "0", "1", "0", "saved", "Jordon Ibe", "Bournemouth", "right", "the right side of the box", "the centre of the goal", "Simon Francis", "0", "NA", "NA", "0", "NA", "0", "0", "NA", "NA", "NA", "0", "NA", "NA", "NA", "0", "NA", "NA", "0", "NA", "0", "NA", "NA", "NA", "0", "NA", "NA", "0", "0", "NA", "NA", "NA", "0", "NA", "NA", "NA", "NA", "2", "83", "0", "NA", "NA", "67"], ["480715", "Arthur Masuaku (West Ham United) wins a free kick on the left wing.", "67'", "AFC Bournemouth", "2", "0", "0", "0", "0", "0", "NA", "NA", "NA", "NA", "NA", "NA", "NA", "0", "NA", "NA", "0", "NA", "0", "0", "NA", "NA", "NA", "0", "NA", "NA", "NA", "0", "NA", "NA", "0", "NA", "1", "Arthur Masuaku", "West Ham United", "NA", "0", "NA", "NA", "0", "0", "NA", "NA", "NA", "0", "NA", "NA", "NA", "NA", "2", "84", "0", "NA", "NA", "67"], ["480715", "Foul by Benik Afobe (Bournemouth).", "67'", "AFC Bournemouth", "2", "0", "0", "0", "0", "0", "NA", "NA", "NA", "NA", "NA", "NA", "NA", "1", "Benik Afobe", "Bournemouth", "0", "NA", "0", "0", "NA", "NA", "NA", "0", "NA", "NA", "NA", "0", "NA", "NA", "0", "NA", "0", "NA", "NA", "NA", "0", "NA", "NA", "0", "0", "NA", "NA", "NA", "0", "NA", "NA", "NA", "NA", "2", "85", "0", "NA", "NA", "67"], ["480715", "Attempt missed. Marko Arnautovic (West Ham United) left footed shot from the centre of the box misses to the left. Assisted by Chicharito.", "70'", "AFC Bournemouth", "2", "0", "0", "0", "1", "0", "missed", "Marko Arnautovic", "West Ham United", "left", "the centre of the box", "left", "Chicharito", "0", "NA", "NA", "0", "NA", "0", "0", "NA", "NA", "NA", "0", "NA", "NA", "NA", "0", "NA", "NA", "0", "NA", "0", "NA", "NA", "NA", "0", "NA", "NA", "0", "0", "NA", "NA", "NA", "0", "NA", "NA", "NA", "NA", "2", "86", "0", "NA", "NA", "70"], ["480715", "Chicharito (West Ham United) wins a free kick in the attacking half.", "71'", "AFC Bournemouth", "2", "0", "0", "0", "0", "0", "NA", "NA", "NA", "NA", "NA", "NA", "NA", "0", "NA", "NA", "0", "NA", "0", "0", "NA", "NA", "NA", "0", "NA", "NA", "NA", "0", "NA", "NA", "0", "NA", "1", "Chicharito", "West Ham United", "attacking half", "0", "NA", "NA", "0", "0", "NA", "NA", "NA", "0", "NA", "NA", "NA", "NA", "2", "87", "0", "NA", "NA", "71"], ["480715", "Foul by Lewis Cook (Bournemouth).", "71'", "AFC Bournemouth", "2", "0", "0", "0", "0", "0", "NA", "NA", "NA", "NA", "NA", "NA", "NA", "1", "Lewis Cook", "Bournemouth", "0", "NA", "0", "0", "NA", "NA", "NA", "0", "NA", "NA", "NA", "0", "NA", "NA", "0", "NA", "0", "NA", "NA", "NA", "0", "NA", "NA", "0", "0", "NA", "NA", "NA", "0", "NA", "NA", "NA", "NA", "2", "88", "0", "NA", "NA", "71"], ["480715", "Lewis Cook (Bournemouth) is shown the yellow card for a bad foul.", "71'", "AFC Bournemouth", "2", "0", "0", "0", "0", "0", "NA", "NA", "NA", "NA", "NA", "NA", "NA", "0", "NA", "NA", "0", "NA", "0", "0", "NA", "NA", "NA", "1", "yellow", "Lewis Cook", "Bournemouth", "0", "NA", "NA", "0", "NA", "0", "NA", "NA", "NA", "0", "NA", "NA", "0", "0", "NA", "NA", "NA", "0", "NA", "NA", "NA", "NA", "2", "89", "0", "NA", "NA", "71"], ["480715", "Attempt missed. Ryan Fraser (Bournemouth) left footed shot from the centre of the box misses to the right. Assisted by Simon Francis with a cross.", "72'", "AFC Bournemouth", "2", "0", "0", "0", "1", "0", "missed", "Ryan Fraser", "Bournemouth", "left", "the centre of the box", "right", "Simon Francis", "0", "NA", "NA", "0", "cross", "0", "0", "NA", "NA", "NA", "0", "NA", "NA", "NA", "0", "NA", "NA", "0", "NA", "0", "NA", "NA", "NA", "0", "NA", "NA", "0", "0", "NA", "NA", "NA", "0", "NA", "NA", "NA", "NA", "2", "90", "0", "NA", "NA", "72"], ["480715", "Callum Wilson (Bournemouth) wins a free kick in the attacking half.", "73'", "AFC Bournemouth", "2", "0", "0", "0", "0", "0", "NA", "NA", "NA", "NA", "NA", "NA", "NA", "0", "NA", "NA", "0", "NA", "0", "0", "NA", "NA", "NA", "0", "NA", "NA", "NA", "0", "NA", "NA", "0", "NA", "1", "Callum Wilson", "Bournemouth", "attacking half", "0", "NA", "NA", "0", "0", "NA", "NA", "NA", "0", "NA", "NA", "NA", "NA", "2", "91", "0", "NA", "NA", "73"], ["480715", "Foul by Angelo Ogbonna (West Ham United).", "73'", "AFC Bournemouth", "2", "0", "0", "0", "0", "0", "NA", "NA", "NA", "NA", "NA", "NA", "NA", "1", "Angelo Ogbonna", "West Ham United", "0", "NA", "0", "0", "NA", "NA", "NA", "0", "NA", "NA", "NA", "0", "NA", "NA", "0", "NA", "0", "NA", "NA", "NA", "0", "NA", "NA", "0", "0", "NA", "NA", "NA", "0", "NA", "NA", "NA", "NA", "2", "92", "0", "NA", "NA", "73"], ["480715", "Foul by Manuel Lanzini (West Ham United).", "74'", "AFC Bournemouth", "2", "0", "0", "0", "0", "0", "NA", "NA", "NA", "NA", "NA", "NA", "NA", "1", "Manuel Lanzini", "West Ham United", "0", "NA", "0", "0", "NA", "NA", "NA", "0", "NA", "NA", "NA", "0", "NA", "NA", "0", "NA", "0", "NA", "NA", "NA", "0", "NA", "NA", "0", "0", "NA", "NA", "NA", "0", "NA", "NA", "NA", "NA", "2", "93", "0", "NA", "NA", "74"], ["480715", "Ryan Fraser (Bournemouth) wins a free kick in the attacking half.", "74'", "AFC Bournemouth", "2", "0", "0", "0", "0", "0", "NA", "NA", "NA", "NA", "NA", "NA", "NA", "0", "NA", "NA", "0", "NA", "0", "0", "NA", "NA", "NA", "0", "NA", "NA", "NA", "0", "NA", "NA", "0", "NA", "1", "Ryan Fraser", "Bournemouth", "attacking half", "0", "NA", "NA", "0", "0", "NA", "NA", "NA", "0", "NA", "NA", "NA", "NA", "2", "94", "0", "NA", "NA", "74"], ["480715", "Delay in match Steve Cook (Bournemouth) because of an injury.", "75'", "AFC Bournemouth", "2", "0", "0", "0", "0", "0", "NA", "NA", "NA", "NA", "NA", "NA", "NA", "0", "NA", "NA", "0", "NA", "0", "0", "NA", "NA", "NA", "0", "NA", "NA", "NA", "0", "NA", "NA", "1", "Bournemouth", "0", "NA", "NA", "NA", "0", "NA", "NA", "0", "0", "NA", "NA", "NA", "0", "NA", "NA", "NA", "NA", "2", "95", "0", "NA", "NA", "75"], ["480715", "Delay over. They are ready to continue.", "77'", "AFC Bournemouth", "2", "0", "0", "0", "0", "0", "NA", "NA", "NA", "NA", "NA", "NA", "NA", "0", "NA", "NA", "0", "NA", "0", "0", "NA", "NA", "NA", "0", "NA", "NA", "NA", "0", "NA", "NA", "0", "NA", "0", "NA", "NA", "NA", "0", "NA", "NA", "0", "0", "NA", "NA", "NA", "0", "NA", "NA", "NA", "NA", "2", "96", "0", "NA", "NA", "77"], ["480715", "Attempt saved. Benik Afobe (Bournemouth) right footed shot from the left side of the six yard box is saved in the bottom left corner. Assisted by Ryan Fraser with a cross.", "78'", "AFC Bournemouth", "2", "0", "0", "0", "1", "0", "saved", "Benik Afobe", "Bournemouth", "right", "the left side of the six yard box", "the bottom left corner", "Ryan Fraser", "0", "NA", "NA", "0", "cross", "0", "0", "NA", "NA", "NA", "0", "NA", "NA", "NA", "0", "NA", "NA", "0", "NA", "0", "NA", "NA", "NA", "0", "NA", "NA", "0", "0", "NA", "NA", "NA", "0", "NA", "NA", "NA", "NA", "2", "97", "0", "NA", "NA", "78"], ["480715", "Attempt saved. Benik Afobe (Bournemouth) right footed shot from the left side of the six yard box is saved in the bottom left corner.", "78'", "AFC Bournemouth", "2", "0", "0", "0", "1", "0", "saved", "Benik Afobe", "Bournemouth", "right", "the left side of the six yard box", "the bottom left corner", "NA", "0", "NA", "NA", "0", "NA", "0", "0", "NA", "NA", "NA", "0", "NA", "NA", "NA", "0", "NA", "NA", "0", "NA", "0", "NA", "NA", "NA", "0", "NA", "NA", "0", "0", "NA", "NA", "NA", "0", "NA", "NA", "NA", "NA", "2", "98", "0", "NA", "NA", "78"], ["480715", "Corner,  Bournemouth. Conceded by Adrián.", "78'", "AFC Bournemouth", "2", "0", "0", "0", "0", "0", "NA", "NA", "NA", "NA", "NA", "NA", "NA", "0", "NA", "NA", "0", "NA", "0", "0", "NA", "NA", "NA", "0", "NA", "NA", "NA", "0", "NA", "NA", "0", "NA", "0", "NA", "NA", "NA", "1", "Bournemouth", "Adrián", "0", "0", "NA", "NA", "NA", "0", "NA", "NA", "NA", "NA", "2", "99", "0", "NA", "NA", "78"], ["480715", "Substitution, West Ham United. Declan Rice replaces Pablo Zabaleta.", "79'", "AFC Bournemouth", "2", "0", "0", "0", "0", "0", "NA", "NA", "NA", "NA", "NA", "NA", "NA", "0", "NA", "NA", "0", "NA", "0", "0", "NA", "NA", "NA", "0", "NA", "NA", "NA", "0", "NA", "NA", "0", "NA", "0", "NA", "NA", "NA", "0", "NA", "NA", "1", "0", "West Ham United", "Declan Rice", "Pablo Zabaleta", "0", "NA", "NA", "NA", "NA", "2", "100", "0", "NA", "NA", "79"], ["480715", "Foul by Nathan Aké (Bournemouth).", "79'", "AFC Bournemouth", "2", "0", "0", "0", "0", "0", "NA", "NA", "NA", "NA", "NA", "NA", "NA", "1", "Nathan Aké", "Bournemouth", "0", "NA", "0", "0", "NA", "NA", "NA", "0", "NA", "NA", "NA", "0", "NA", "NA", "0", "NA", "0", "NA", "NA", "NA", "0", "NA", "NA", "0", "0", "NA", "NA", "NA", "0", "NA", "NA", "NA", "NA", "2", "101", "0", "NA", "NA", "79"], ["480715", "Manuel Lanzini (West Ham United) wins a free kick in the defensive half.", "79'", "AFC Bournemouth", "2", "0", "0", "0", "0", "0", "NA", "NA", "NA", "NA", "NA", "NA", "NA", "0", "NA", "NA", "0", "NA", "0", "0", "NA", "NA", "NA", "0", "NA", "NA", "NA", "0", "NA", "NA", "0", "NA", "1", "Manuel Lanzini", "West Ham United", "defensive half", "0", "NA", "NA", "0", "0", "NA", "NA", "NA", "0", "NA", "NA", "NA", "NA", "2", "102", "0", "NA", "NA", "79"], ["480715", "Nathan Aké (Bournemouth) is shown the yellow card for a bad foul.", "79'", "AFC Bournemouth", "2", "0", "0", "0", "0", "0", "NA", "NA", "NA", "NA", "NA", "NA", "NA", "0", "NA", "NA", "0", "NA", "0", "0", "NA", "NA", "NA", "1", "yellow", "Nathan Aké", "Bournemouth", "0", "NA", "NA", "0", "NA", "0", "NA", "NA", "NA", "0", "NA", "NA", "0", "0", "NA", "NA", "NA", "0", "NA", "NA", "NA", "NA", "2", "103", "0", "NA", "NA", "79"], ["480715", "Attempt saved. Andy Carroll (West Ham United) left footed shot from outside the box is saved in the bottom right corner.", "80'", "AFC Bournemouth", "2", "0", "0", "0", "1", "0", "saved", "Andy Carroll", "West Ham United", "left", "outside the box", "the bottom right corner", "NA", "0", "NA", "NA", "0", "NA", "0", "0", "NA", "NA", "NA", "0", "NA", "NA", "NA", "0", "NA", "NA", "0", "NA", "0", "NA", "NA", "NA", "0", "NA", "NA", "0", "0", "NA", "NA", "NA", "0", "NA", "NA", "NA", "NA", "2", "104", "0", "NA", "NA", "80"], ["480715", "Attempt saved. Jordon Ibe (Bournemouth) right footed shot from the centre of the box is saved in the bottom right corner. Assisted by Callum Wilson.", "80'", "AFC Bournemouth", "2", "0", "0", "0", "1", "0", "saved", "Jordon Ibe", "Bournemouth", "right", "the centre of the box", "the bottom right corner", "Callum Wilson", "0", "NA", "NA", "0", "NA", "0", "0", "NA", "NA", "NA", "0", "NA", "NA", "NA", "0", "NA", "NA", "0", "NA", "0", "NA", "NA", "NA", "0", "NA", "NA", "0", "0", "NA", "NA", "NA", "0", "NA", "NA", "NA", "NA", "2", "105", "0", "NA", "NA", "80"], ["480715", "Corner,  Bournemouth. Conceded by Adrián.", "80'", "AFC Bournemouth", "2", "0", "0", "0", "0", "0", "NA", "NA", "NA", "NA", "NA", "NA", "NA", "0", "NA", "NA", "0", "NA", "0", "0", "NA", "NA", "NA", "0", "NA", "NA", "NA", "0", "NA", "NA", "0", "NA", "0", "NA", "NA", "NA", "1", "Bournemouth", "Adrián", "0", "0", "NA", "NA", "NA", "0", "NA", "NA", "NA", "NA", "2", "106", "0", "NA", "NA", "80"], ["480715", "Goal!  Bournemouth 2, West Ham United 2. Marko Arnautovic (West Ham United) left footed shot from outside the box to the bottom left corner.", "81'", "AFC Bournemouth", "2", "0", "0", "0", "1", "0", "goal", "Marko Arnautovic", "West Ham United", "left", "outside the box", "bottom left corner", "NA", "0", "NA", "NA", "0", "NA", "0", "0", "NA", "NA", "NA", "0", "NA", "NA", "NA", "0", "NA", "NA", "0", "NA", "0", "NA", "NA", "NA", "0", "NA", "NA", "0", "0", "NA", "NA", "NA", "0", "NA", "NA", "NA", "NA", "2", "107", "0", "NA", "NA", "81"], ["480715", "Callum Wilson (Bournemouth) wins a free kick in the defensive half.", "83'", "AFC Bournemouth", "2", "0", "0", "0", "0", "0", "NA", "NA", "NA", "NA", "NA", "NA", "NA", "0", "NA", "NA", "0", "NA", "0", "0", "NA", "NA", "NA", "0", "NA", "NA", "NA", "0", "NA", "NA", "0", "NA", "1", "Callum Wilson", "Bournemouth", "defensive half", "0", "NA", "NA", "0", "0", "NA", "NA", "NA", "0", "NA", "NA", "NA", "NA", "2", "108", "0", "NA", "NA", "83"], ["480715", "Foul by Angelo Ogbonna (West Ham United).", "83'", "AFC Bournemouth", "2", "0", "0", "0", "0", "0", "NA", "NA", "NA", "NA", "NA", "NA", "NA", "1", "Angelo Ogbonna", "West Ham United", "0", "NA", "0", "0", "NA", "NA", "NA", "0", "NA", "NA", "NA", "0", "NA", "NA", "0", "NA", "0", "NA", "NA", "NA", "0", "NA", "NA", "0", "0", "NA", "NA", "NA", "0", "NA", "NA", "NA", "NA", "2", "109", "0", "NA", "NA", "83"], ["480715", "Attempt missed. Callum Wilson (Bournemouth) header from the centre of the box misses to the left. Assisted by Simon Francis with a cross.", "84'", "AFC Bournemouth", "2", "0", "0", "0", "1", "0", "missed", "Callum Wilson", "Bournemouth", "header", "the centre of the box", "left", "Simon Francis", "0", "NA", "NA", "0", "cross", "0", "0", "NA", "NA", "NA", "0", "NA", "NA", "NA", "0", "NA", "NA", "0", "NA", "0", "NA", "NA", "NA", "0", "NA", "NA", "0", "0", "NA", "NA", "NA", "0", "NA", "NA", "NA", "NA", "2", "110", "0", "NA", "NA", "84"], ["480715", "Substitution, Bournemouth. Marc Pugh replaces Ryan Fraser.", "86'", "AFC Bournemouth", "2", "0", "0", "0", "0", "0", "NA", "NA", "NA", "NA", "NA", "NA", "NA", "0", "NA", "NA", "0", "NA", "0", "0", "NA", "NA", "NA", "0", "NA", "NA", "NA", "0", "NA", "NA", "0", "NA", "0", "NA", "NA", "NA", "0", "NA", "NA", "1", "0", "Bournemouth", "Marc Pugh", "Ryan Fraser", "0", "NA", "NA", "NA", "NA", "2", "111", "0", "NA", "NA", "86"], ["480715", "Hand ball by Aaron Cresswell (West Ham United).", "87'", "AFC Bournemouth", "2", "0", "0", "0", "0", "0", "NA", "NA", "NA", "NA", "NA", "NA", "NA", "0", "NA", "NA", "0", "NA", "0", "0", "NA", "NA", "NA", "0", "NA", "NA", "NA", "0", "NA", "NA", "0", "NA", "0", "NA", "NA", "NA", "0", "NA", "NA", "0", "0", "NA", "NA", "NA", "0", "NA", "NA", "NA", "NA", "2", "112", "0", "NA", "NA", "87"], ["480715", "Angelo Ogbonna (West Ham United) is shown the yellow card.", "87'", "AFC Bournemouth", "2", "0", "0", "0", "0", "0", "NA", "NA", "NA", "NA", "NA", "NA", "NA", "0", "NA", "NA", "0", "NA", "0", "0", "NA", "NA", "NA", "1", "yellow", "Angelo Ogbonna", "West Ham United", "0", "NA", "NA", "0", "NA", "0", "NA", "NA", "NA", "0", "NA", "NA", "0", "0", "NA", "NA", "NA", "0", "NA", "NA", "NA", "NA", "2", "113", "0", "NA", "NA", "87"], ["480715", "Attempt missed. Jordon Ibe (Bournemouth) right footed shot from outside the box is too high from a direct free kick.", "88'", "AFC Bournemouth", "2", "0", "0", "0", "1", "0", "missed", "Jordon Ibe", "Bournemouth", "right", "outside the box", "too high", "NA", "0", "NA", "NA", "0", "NA", "0", "0", "NA", "NA", "NA", "0", "NA", "NA", "NA", "0", "NA", "NA", "0", "NA", "0", "NA", "NA", "NA", "0", "NA", "NA", "0", "0", "NA", "NA", "NA", "0", "NA", "NA", "NA", "NA", "2", "114", "0", "NA", "NA", "88"], ["480715", "Attempt saved. Chicharito (West Ham United) right footed shot from the right side of the six yard box is saved in the centre of the goal. Assisted by Arthur Masuaku with a cross.", "89'", "AFC Bournemouth", "2", "0", "0", "0", "1", "0", "saved", "Chicharito", "West Ham United", "right", "the right side of the six yard box", "the centre of the goal", "Arthur Masuaku", "0", "NA", "NA", "0", "cross", "0", "0", "NA", "NA", "NA", "0", "NA", "NA", "NA", "0", "NA", "NA", "0", "NA", "0", "NA", "NA", "NA", "0", "NA", "NA", "0", "0", "NA", "NA", "NA", "0", "NA", "NA", "NA", "NA", "2", "115", "0", "NA", "NA", "89"], ["480715", "Goal!  Bournemouth 2, West Ham United 3. Marko Arnautovic (West Ham United) right footed shot from very close range to the bottom left corner.", "89'", "AFC Bournemouth", "2", "0", "0", "0", "1", "0", "goal", "Marko Arnautovic", "West Ham United", "right", "right shot very close range", "bottom left corner", "NA", "0", "NA", "NA", "0", "NA", "0", "0", "NA", "NA", "NA", "0", "NA", "NA", "NA", "0", "NA", "NA", "0", "NA", "0", "NA", "NA", "NA", "0", "NA", "NA", "0", "0", "NA", "NA", "NA", "0", "NA", "NA", "NA", "NA", "2", "116", "0", "NA", "NA", "89"], ["480715", "Goal!  Bournemouth 3, West Ham United 3. Callum Wilson (Bournemouth) with an attempt from very close range to the bottom right corner. Assisted by Nathan Aké with a headed pass.", "90'+3'", "AFC Bournemouth", "3", "0", "0", "0", "1", "0", "goal", "Callum Wilson", "Bournemouth", "NA", "with an attempt very close range", "bottom right corner", "Nathan Aké", "0", "NA", "NA", "0", "NA", "0", "0", "NA", "NA", "NA", "0", "NA", "NA", "NA", "0", "NA", "NA", "0", "NA", "0", "NA", "NA", "NA", "0", "NA", "NA", "0", "0", "NA", "NA", "NA", "0", "NA", "NA", "NA", "NA", "2", "117", "1", "NA", "NA", "93"], ["480715", "Foul by Dan Gosling (Bournemouth).", "90'+5'", "AFC Bournemouth", "3", "0", "0", "0", "0", "0", "NA", "NA", "NA", "NA", "NA", "NA", "NA", "1", "Dan Gosling", "Bournemouth", "0", "NA", "0", "0", "NA", "NA", "NA", "0", "NA", "NA", "NA", "0", "NA", "NA", "0", "NA", "0", "NA", "NA", "NA", "0", "NA", "NA", "0", "0", "NA", "NA", "NA", "0", "NA", "NA", "NA", "NA", "2", "118", "1", "NA", "NA", "95"], ["480715", "Marko Arnautovic (West Ham United) wins a free kick in the defensive half.", "90'+5'", "AFC Bournemouth", "3", "0", "0", "0", "0", "0", "NA", "NA", "NA", "NA", "NA", "NA", "NA", "0", "NA", "NA", "0", "NA", "0", "0", "NA", "NA", "NA", "0", "NA", "NA", "NA", "0", "NA", "NA", "0", "NA", "1", "Marko Arnautovic", "West Ham United", "defensive half", "0", "NA", "NA", "0", "0", "NA", "NA", "NA", "0", "NA", "NA", "NA", "NA", "2", "119", "1", "NA", "NA", "95"], ["480715", "Second Half ends, Bournemouth 3, West Ham United 3.", "90'+7'", "AFC Bournemouth", "3", "1", "0", "0", "0", "0", "NA", "NA", "NA", "NA", "NA", "NA", "NA", "0", "NA", "NA", "0", "NA", "0", "0", "NA", "NA", "NA", "0", "NA", "NA", "NA", "0", "NA", "NA", "0", "NA", "0", "NA", "NA", "NA", "0", "NA", "NA", "0", "0", "NA", "NA", "NA", "0", "NA", "NA", "NA", "NA", "2", "120", "1", "NA", "NA", "97"], ["480715", "Match ends, Bournemouth 3, West Ham United 3.", "90'+7'", "AFC Bournemouth", "3", "0", "1", "0", "0", "0", "NA", "NA", "NA", "NA", "NA", "NA", "NA", "0", "NA", "NA", "0", "NA", "0", "0", "NA", "NA", "NA", "0", "NA", "NA", "NA", "0", "NA", "NA", "0", "NA", "0", "NA", "NA", "NA", "0", "NA", "NA", "0", "0", "NA", "NA", "NA", "0", "NA", "NA", "NA", "NA", "2", "121", "1", "NA", "NA", "97"], ["480715", "Match ends, Bournemouth 3, West Ham United 3.", "90'+7'", "AFC Bournemouth", "3", "0", "1", "0", "0", "0", "NA", "NA", "NA", "NA", "NA", "NA", "NA", "0", "NA", "NA", "0", "NA", "0", "0", "NA", "NA", "NA", "0", "NA", "NA", "NA", "0", "NA", "NA", "0", "NA", "0", "NA", "NA", "NA", "0", "NA", "NA", "0", "0", "NA", "NA", "NA", "0", "NA", "NA", "NA", "NA", "2", "122", "1", "NA", "NA", "97"]], "Lineup": {"Home Player 9": "Joshua King", "Home Player 8": "Jordon Ibe", "Home Player 5": "Simon Francis", "Home Player 4": "Steve Cook", "Home Player 7": "Dan Gosling", "Home Player 6": "Ryan Fraser", "Home Player 1": "Nathan Ake", "Home Player 3": "Lewis Cook", "Home Player 2": "Asmir Begovic", "Away Player 10": "Angelo Ogbonna", "Away Player 11": "Pablo Zabaleta", "Away Player 8": "Arthur Masuaku", "Away Player 9": "Pedro Obiang", "Away Player 1": "Adrian", "Away Player 2": "Marko Arnautovic", "Away Player 3": "Andre Ayew", "Away Player 4": "James Collins", "Away Player 5": "Aaron Cresswell", "Away Player 6": "Cheikhou Kouyate", "Away Player 7": "Manuel Lanzini", "Game ID": "g_1_hldcALka", "Home Player 11": "Callum Wilson", "Home Player 10": "Adam Smith"}}