{"Date": "2018-01-04", "Home Team": "Tottenham Hotspur", "Away Team": "West Ham United", "Stats": {"Away Team Shots": 3, "Away Team Red Cards": 0, "Home Team Yellow Cards": 0, "Away Team Fouls Committed": 6, "Away Team Corners": 1, "Referee": "M Dean", "Home Team Fouls Committed": 10, "Half Time Home Team Goals": 0, "Half Time Away Team Goals": 0, "Home Team Red Cards": 0, "Home Team Shots": 31, "Div": "E0", "Home Team Corners": 7, "Full Time Away Team Goals": 1, "Full Time Result": "D", "Away Team Shots on Target": 1, "Full Time Home Team Goals": 1, "Half Time Result": "D", "Away Team Yellow Cards": 2, "Home Team Shots on Target": 8}, "Commentary": [["480705", "First Half begins.", "-", "0", "0", "0", "0", "1", "0", "0", "NA", "NA", "NA", "NA", "NA", "NA", "NA", "0", "NA", "NA", "0", "NA", "0", "0", "NA", "NA", "NA", "0", "NA", "NA", "NA", "0", "NA", "NA", "0", "NA", "0", "NA", "NA", "NA", "0", "NA", "NA", "0", "0", "NA", "NA", "NA", "0", "NA", "NA", "NA", "NA", "1", "1", "0", "NA", "NA", "NA"], ["480705", "Lineups are announced and players are warming up.", "-", "0", "0", "0", "0", "0", "0", "0", "NA", "NA", "NA", "NA", "NA", "NA", "NA", "0", "NA", "NA", "0", "NA", "0", "0", "NA", "NA", "NA", "0", "NA", "NA", "NA", "0", "NA", "NA", "0", "NA", "0", "NA", "NA", "NA", "0", "NA", "NA", "0", "0", "NA", "NA", "NA", "0", "NA", "NA", "NA", "NA", "1", "2", "0", "NA", "NA", "NA"], ["480705", "Dele Alli (Tottenham Hotspur) wins a free kick on the right wing.", "3'", "0", "0", "0", "0", "0", "0", "0", "NA", "NA", "NA", "NA", "NA", "NA", "NA", "0", "NA", "NA", "0", "NA", "0", "0", "NA", "NA", "NA", "0", "NA", "NA", "NA", "0", "NA", "NA", "0", "NA", "1", "Dele Alli", "Tottenham Hotspur", "NA", "0", "NA", "NA", "0", "0", "NA", "NA", "NA", "0", "NA", "NA", "NA", "NA", "1", "3", "0", "NA", "NA", "3"], ["480705", "Foul by Arthur Masuaku (West Ham United).", "3'", "0", "0", "0", "0", "0", "0", "0", "NA", "NA", "NA", "NA", "NA", "NA", "NA", "1", "Arthur Masuaku", "West Ham United", "0", "NA", "0", "0", "NA", "NA", "NA", "0", "NA", "NA", "NA", "0", "NA", "NA", "0", "NA", "0", "NA", "NA", "NA", "0", "NA", "NA", "0", "0", "NA", "NA", "NA", "0", "NA", "NA", "NA", "NA", "1", "4", "0", "NA", "NA", "3"], ["480705", "Attempt missed. Harry Kane (Tottenham Hotspur) left footed shot from the left side of the six yard box misses to the right.", "4'", "0", "0", "0", "0", "0", "1", "0", "missed", "Harry Kane", "Tottenham Hotspur", "left", "the left side of the six yard box", "right", "NA", "0", "NA", "NA", "0", "NA", "0", "0", "NA", "NA", "NA", "0", "NA", "NA", "NA", "0", "NA", "NA", "0", "NA", "0", "NA", "NA", "NA", "0", "NA", "NA", "0", "0", "NA", "NA", "NA", "0", "NA", "NA", "NA", "NA", "1", "5", "0", "NA", "NA", "4"], ["480705", "Corner,  Tottenham Hotspur. Conceded by Declan Rice.", "4'", "0", "0", "0", "0", "0", "0", "0", "NA", "NA", "NA", "NA", "NA", "NA", "NA", "0", "NA", "NA", "0", "NA", "0", "0", "NA", "NA", "NA", "0", "NA", "NA", "NA", "0", "NA", "NA", "0", "NA", "0", "NA", "NA", "NA", "1", "Tottenham Hotspur", "Declan Rice", "0", "0", "NA", "NA", "NA", "0", "NA", "NA", "NA", "NA", "1", "6", "0", "NA", "NA", "4"], ["480705", "Attempt blocked. Davinson Sánchez (Tottenham Hotspur) right footed shot from the centre of the box is blocked. Assisted by Eric Dier.", "4'", "0", "0", "0", "0", "0", "1", "0", "blocked", "Davinson Sánchez", "Tottenham Hotspur", "right", "the centre of the box", "NA", "Eric Dier", "0", "NA", "NA", "0", "NA", "0", "0", "NA", "NA", "NA", "0", "NA", "NA", "NA", "0", "NA", "NA", "0", "NA", "0", "NA", "NA", "NA", "0", "NA", "NA", "0", "0", "NA", "NA", "NA", "0", "NA", "NA", "NA", "NA", "1", "7", "0", "NA", "NA", "4"], ["480705", "Corner,  Tottenham Hotspur. Conceded by Declan Rice.", "5'", "0", "0", "0", "0", "0", "0", "0", "NA", "NA", "NA", "NA", "NA", "NA", "NA", "0", "NA", "NA", "0", "NA", "0", "0", "NA", "NA", "NA", "0", "NA", "NA", "NA", "0", "NA", "NA", "0", "NA", "0", "NA", "NA", "NA", "1", "Tottenham Hotspur", "Declan Rice", "0", "0", "NA", "NA", "NA", "0", "NA", "NA", "NA", "NA", "1", "8", "0", "NA", "NA", "5"], ["480705", "Foul by Dele Alli (Tottenham Hotspur).", "7'", "0", "0", "0", "0", "0", "0", "0", "NA", "NA", "NA", "NA", "NA", "NA", "NA", "1", "Dele Alli", "Tottenham Hotspur", "0", "NA", "0", "0", "NA", "NA", "NA", "0", "NA", "NA", "NA", "0", "NA", "NA", "0", "NA", "0", "NA", "NA", "NA", "0", "NA", "NA", "0", "0", "NA", "NA", "NA", "0", "NA", "NA", "NA", "NA", "1", "9", "0", "NA", "NA", "7"], ["480705", "Pedro Obiang (West Ham United) wins a free kick in the defensive half.", "7'", "0", "0", "0", "0", "0", "0", "0", "NA", "NA", "NA", "NA", "NA", "NA", "NA", "0", "NA", "NA", "0", "NA", "0", "0", "NA", "NA", "NA", "0", "NA", "NA", "NA", "0", "NA", "NA", "0", "NA", "1", "Pedro Obiang", "West Ham United", "defensive half", "0", "NA", "NA", "0", "0", "NA", "NA", "NA", "0", "NA", "NA", "NA", "NA", "1", "10", "0", "NA", "NA", "7"], ["480705", "Foul by Son Heung-Min (Tottenham Hotspur).", "8'", "0", "0", "0", "0", "0", "0", "0", "NA", "NA", "NA", "NA", "NA", "NA", "NA", "1", "Son Heung-Min", "Tottenham Hotspur", "0", "NA", "0", "0", "NA", "NA", "NA", "0", "NA", "NA", "NA", "0", "NA", "NA", "0", "NA", "0", "NA", "NA", "NA", "0", "NA", "NA", "0", "0", "NA", "NA", "NA", "0", "NA", "NA", "NA", "NA", "1", "11", "0", "NA", "NA", "8"], ["480705", "Pablo Zabaleta (West Ham United) wins a free kick in the attacking half.", "8'", "0", "0", "0", "0", "0", "0", "0", "NA", "NA", "NA", "NA", "NA", "NA", "NA", "0", "NA", "NA", "0", "NA", "0", "0", "NA", "NA", "NA", "0", "NA", "NA", "NA", "0", "NA", "NA", "0", "NA", "1", "Pablo Zabaleta", "West Ham United", "attacking half", "0", "NA", "NA", "0", "0", "NA", "NA", "NA", "0", "NA", "NA", "NA", "NA", "1", "12", "0", "NA", "NA", "8"], ["480705", "Christian Eriksen (Tottenham Hotspur) wins a free kick in the defensive half.", "9'", "0", "0", "0", "0", "0", "0", "0", "NA", "NA", "NA", "NA", "NA", "NA", "NA", "0", "NA", "NA", "0", "NA", "0", "0", "NA", "NA", "NA", "0", "NA", "NA", "NA", "0", "NA", "NA", "0", "NA", "1", "Christian Eriksen", "Tottenham Hotspur", "defensive half", "0", "NA", "NA", "0", "0", "NA", "NA", "NA", "0", "NA", "NA", "NA", "NA", "1", "13", "0", "NA", "NA", "9"], ["480705", "Foul by Pedro Obiang (West Ham United).", "9'", "0", "0", "0", "0", "0", "0", "0", "NA", "NA", "NA", "NA", "NA", "NA", "NA", "1", "Pedro Obiang", "West Ham United", "0", "NA", "0", "0", "NA", "NA", "NA", "0", "NA", "NA", "NA", "0", "NA", "NA", "0", "NA", "0", "NA", "NA", "NA", "0", "NA", "NA", "0", "0", "NA", "NA", "NA", "0", "NA", "NA", "NA", "NA", "1", "14", "0", "NA", "NA", "9"], ["480705", "Offside, West Ham United. Mark Noble tries a through ball, but Chicharito is caught offside.", "13'", "0", "0", "0", "0", "0", "0", "0", "NA", "NA", "NA", "NA", "NA", "NA", "NA", "0", "NA", "NA", "0", "NA", "0", "1", "West Ham United", "Chicharito", "Mark Noble", "0", "NA", "NA", "NA", "0", "NA", "NA", "0", "NA", "0", "NA", "NA", "NA", "0", "NA", "NA", "0", "0", "NA", "NA", "NA", "0", "NA", "NA", "NA", "NA", "1", "15", "0", "NA", "NA", "13"], ["480705", "Attempt blocked. Harry Kane (Tottenham Hotspur) right footed shot from the centre of the box is blocked. Assisted by Serge Aurier.", "15'", "0", "0", "0", "0", "0", "1", "0", "blocked", "Harry Kane", "Tottenham Hotspur", "right", "the centre of the box", "NA", "Serge Aurier", "0", "NA", "NA", "0", "NA", "0", "0", "NA", "NA", "NA", "0", "NA", "NA", "NA", "0", "NA", "NA", "0", "NA", "0", "NA", "NA", "NA", "0", "NA", "NA", "0", "0", "NA", "NA", "NA", "0", "NA", "NA", "NA", "NA", "1", "16", "0", "NA", "NA", "15"], ["480705", "Attempt blocked. Christian Eriksen (Tottenham Hotspur) left footed shot from the centre of the box is blocked.", "15'", "0", "0", "0", "0", "0", "1", "0", "blocked", "Christian Eriksen", "Tottenham Hotspur", "left", "the centre of the box", "NA", "NA", "0", "NA", "NA", "0", "NA", "0", "0", "NA", "NA", "NA", "0", "NA", "NA", "NA", "0", "NA", "NA", "0", "NA", "0", "NA", "NA", "NA", "0", "NA", "NA", "0", "0", "NA", "NA", "NA", "0", "NA", "NA", "NA", "NA", "1", "17", "0", "NA", "NA", "15"], ["480705", "Offside, Tottenham Hotspur. Christian Eriksen tries a through ball, but Harry Kane is caught offside.", "16'", "0", "0", "0", "0", "0", "0", "0", "NA", "NA", "NA", "NA", "NA", "NA", "NA", "0", "NA", "NA", "0", "NA", "0", "1", "Tottenham Hotspur", "Harry Kane", "Christian Eriksen", "0", "NA", "NA", "NA", "0", "NA", "NA", "0", "NA", "0", "NA", "NA", "NA", "0", "NA", "NA", "0", "0", "NA", "NA", "NA", "0", "NA", "NA", "NA", "NA", "1", "18", "0", "NA", "NA", "16"], ["480705", "Corner,  Tottenham Hotspur. Conceded by Pablo Zabaleta.", "19'", "0", "0", "0", "0", "0", "0", "0", "NA", "NA", "NA", "NA", "NA", "NA", "NA", "0", "NA", "NA", "0", "NA", "0", "0", "NA", "NA", "NA", "0", "NA", "NA", "NA", "0", "NA", "NA", "0", "NA", "0", "NA", "NA", "NA", "1", "Tottenham Hotspur", "Pablo Zabaleta", "0", "0", "NA", "NA", "NA", "0", "NA", "NA", "NA", "NA", "1", "19", "0", "NA", "NA", "19"], ["480705", "Attempt saved. Harry Kane (Tottenham Hotspur) right footed shot from outside the box is saved in the bottom right corner. Assisted by Dele Alli.", "28'", "0", "0", "0", "0", "0", "1", "0", "saved", "Harry Kane", "Tottenham Hotspur", "right", "outside the box", "the bottom right corner", "Dele Alli", "0", "NA", "NA", "0", "NA", "0", "0", "NA", "NA", "NA", "0", "NA", "NA", "NA", "0", "NA", "NA", "0", "NA", "0", "NA", "NA", "NA", "0", "NA", "NA", "0", "0", "NA", "NA", "NA", "0", "NA", "NA", "NA", "NA", "1", "20", "0", "NA", "NA", "28"], ["480705", "Attempt missed. Eric Dier (Tottenham Hotspur) right footed shot from outside the box is high and wide to the right. Assisted by Christian Eriksen.", "28'", "0", "0", "0", "0", "0", "1", "0", "missed", "Eric Dier", "Tottenham Hotspur", "right", "outside the box", "high and wide to the right", "Christian Eriksen", "0", "NA", "NA", "0", "NA", "0", "0", "NA", "NA", "NA", "0", "NA", "NA", "NA", "0", "NA", "NA", "0", "NA", "0", "NA", "NA", "NA", "0", "NA", "NA", "0", "0", "NA", "NA", "NA", "0", "NA", "NA", "NA", "NA", "1", "21", "0", "NA", "NA", "28"], ["480705", "Attempt saved. Son Heung-Min (Tottenham Hotspur) left footed shot from a difficult angle on the left is saved in the bottom right corner. Assisted by Christian Eriksen.", "29'", "0", "0", "0", "0", "0", "1", "0", "saved", "Son Heung-Min", "Tottenham Hotspur", "left", "NA", "the bottom right corner", "Christian Eriksen", "0", "NA", "NA", "0", "NA", "0", "0", "NA", "NA", "NA", "0", "NA", "NA", "NA", "0", "NA", "NA", "0", "NA", "0", "NA", "NA", "NA", "0", "NA", "NA", "0", "0", "NA", "NA", "NA", "0", "NA", "NA", "NA", "NA", "1", "22", "0", "NA", "NA", "29"], ["480705", "Attempt missed. Christian Eriksen (Tottenham Hotspur) right footed shot from outside the box is close, but misses to the right. Assisted by Harry Kane.", "30'", "0", "0", "0", "0", "0", "1", "0", "missed", "Christian Eriksen", "Tottenham Hotspur", "right", "outside the box", "close, but right", "Harry Kane", "0", "NA", "NA", "0", "NA", "0", "0", "NA", "NA", "NA", "0", "NA", "NA", "NA", "0", "NA", "NA", "0", "NA", "0", "NA", "NA", "NA", "0", "NA", "NA", "0", "0", "NA", "NA", "NA", "0", "NA", "NA", "NA", "NA", "1", "23", "0", "NA", "NA", "30"], ["480705", "Attempt blocked. Christian Eriksen (Tottenham Hotspur) right footed shot from outside the box is blocked. Assisted by Ben Davies.", "35'", "0", "0", "0", "0", "0", "1", "0", "blocked", "Christian Eriksen", "Tottenham Hotspur", "right", "outside the box", "NA", "Ben Davies", "0", "NA", "NA", "0", "NA", "0", "0", "NA", "NA", "NA", "0", "NA", "NA", "NA", "0", "NA", "NA", "0", "NA", "0", "NA", "NA", "NA", "0", "NA", "NA", "0", "0", "NA", "NA", "NA", "0", "NA", "NA", "NA", "NA", "1", "24", "0", "NA", "NA", "35"], ["480705", "Attempt missed. Serge Aurier (Tottenham Hotspur) right footed shot from outside the box is too high.", "37'", "0", "0", "0", "0", "0", "1", "0", "missed", "Serge Aurier", "Tottenham Hotspur", "right", "outside the box", "too high", "NA", "0", "NA", "NA", "0", "NA", "0", "0", "NA", "NA", "NA", "0", "NA", "NA", "NA", "0", "NA", "NA", "0", "NA", "0", "NA", "NA", "NA", "0", "NA", "NA", "0", "0", "NA", "NA", "NA", "0", "NA", "NA", "NA", "NA", "1", "25", "0", "NA", "NA", "37"], ["480705", "Chicharito (West Ham United) wins a free kick on the right wing.", "38'", "0", "0", "0", "0", "0", "0", "0", "NA", "NA", "NA", "NA", "NA", "NA", "NA", "0", "NA", "NA", "0", "NA", "0", "0", "NA", "NA", "NA", "0", "NA", "NA", "NA", "0", "NA", "NA", "0", "NA", "1", "Chicharito", "West Ham United", "NA", "0", "NA", "NA", "0", "0", "NA", "NA", "NA", "0", "NA", "NA", "NA", "NA", "1", "26", "0", "NA", "NA", "38"], ["480705", "Foul by Jan Vertonghen (Tottenham Hotspur).", "38'", "0", "0", "0", "0", "0", "0", "0", "NA", "NA", "NA", "NA", "NA", "NA", "NA", "1", "Jan Vertonghen", "Tottenham Hotspur", "0", "NA", "0", "0", "NA", "NA", "NA", "0", "NA", "NA", "NA", "0", "NA", "NA", "0", "NA", "0", "NA", "NA", "NA", "0", "NA", "NA", "0", "0", "NA", "NA", "NA", "0", "NA", "NA", "NA", "NA", "1", "27", "0", "NA", "NA", "38"], ["480705", "Foul by Moussa Sissoko (Tottenham Hotspur).", "42'", "0", "0", "0", "0", "0", "0", "0", "NA", "NA", "NA", "NA", "NA", "NA", "NA", "1", "Moussa Sissoko", "Tottenham Hotspur", "0", "NA", "0", "0", "NA", "NA", "NA", "0", "NA", "NA", "NA", "0", "NA", "NA", "0", "NA", "0", "NA", "NA", "NA", "0", "NA", "NA", "0", "0", "NA", "NA", "NA", "0", "NA", "NA", "NA", "NA", "1", "28", "0", "NA", "NA", "42"], ["480705", "Manuel Lanzini (West Ham United) wins a free kick in the defensive half.", "42'", "0", "0", "0", "0", "0", "0", "0", "NA", "NA", "NA", "NA", "NA", "NA", "NA", "0", "NA", "NA", "0", "NA", "0", "0", "NA", "NA", "NA", "0", "NA", "NA", "NA", "0", "NA", "NA", "0", "NA", "1", "Manuel Lanzini", "West Ham United", "defensive half", "0", "NA", "NA", "0", "0", "NA", "NA", "NA", "0", "NA", "NA", "NA", "NA", "1", "29", "0", "NA", "NA", "42"], ["480705", "Foul by Serge Aurier (Tottenham Hotspur).", "44'", "0", "0", "0", "0", "0", "0", "0", "NA", "NA", "NA", "NA", "NA", "NA", "NA", "1", "Serge Aurier", "Tottenham Hotspur", "0", "NA", "0", "0", "NA", "NA", "NA", "0", "NA", "NA", "NA", "0", "NA", "NA", "0", "NA", "0", "NA", "NA", "NA", "0", "NA", "NA", "0", "0", "NA", "NA", "NA", "0", "NA", "NA", "NA", "NA", "1", "30", "0", "NA", "NA", "44"], ["480705", "Mark Noble (West Ham United) wins a free kick in the defensive half.", "44'", "0", "0", "0", "0", "0", "0", "0", "NA", "NA", "NA", "NA", "NA", "NA", "NA", "0", "NA", "NA", "0", "NA", "0", "0", "NA", "NA", "NA", "0", "NA", "NA", "NA", "0", "NA", "NA", "0", "NA", "1", "Mark Noble", "West Ham United", "defensive half", "0", "NA", "NA", "0", "0", "NA", "NA", "NA", "0", "NA", "NA", "NA", "NA", "1", "31", "0", "NA", "NA", "44"], ["480705", "Attempt saved. Christian Eriksen (Tottenham Hotspur) right footed shot from outside the box is saved in the top centre of the goal. Assisted by Dele Alli.", "45'", "0", "0", "0", "0", "0", "1", "0", "saved", "Christian Eriksen", "Tottenham Hotspur", "right", "outside the box", "the top centre of the goal", "Dele Alli", "0", "NA", "NA", "0", "NA", "0", "0", "NA", "NA", "NA", "0", "NA", "NA", "NA", "0", "NA", "NA", "0", "NA", "0", "NA", "NA", "NA", "0", "NA", "NA", "0", "0", "NA", "NA", "NA", "0", "NA", "NA", "NA", "NA", "1", "32", "0", "NA", "NA", "45"], ["480705", "Corner,  Tottenham Hotspur. Conceded by Adrián.", "45'", "0", "0", "0", "0", "0", "0", "0", "NA", "NA", "NA", "NA", "NA", "NA", "NA", "0", "NA", "NA", "0", "NA", "0", "0", "NA", "NA", "NA", "0", "NA", "NA", "NA", "0", "NA", "NA", "0", "NA", "0", "NA", "NA", "NA", "1", "Tottenham Hotspur", "Adrián", "0", "0", "NA", "NA", "NA", "0", "NA", "NA", "NA", "NA", "1", "33", "0", "NA", "NA", "45"], ["480705", "Attempt missed. Dele Alli (Tottenham Hotspur) header from the centre of the box misses to the left. Assisted by Ben Davies with a cross following a corner.", "45'", "0", "0", "0", "0", "0", "1", "0", "missed", "Dele Alli", "Tottenham Hotspur", "header", "the centre of the box", "left", "Ben Davies", "0", "NA", "NA", "0", "cross", "1", "0", "NA", "NA", "NA", "0", "NA", "NA", "NA", "0", "NA", "NA", "0", "NA", "0", "NA", "NA", "NA", "0", "NA", "NA", "0", "0", "NA", "NA", "NA", "0", "NA", "NA", "NA", "NA", "1", "34", "0", "NA", "NA", "45"], ["480705", "First Half ends, Tottenham Hotspur 0, West Ham United 0.", "45'+1'", "0", "0", "1", "0", "0", "0", "0", "NA", "NA", "NA", "NA", "NA", "NA", "NA", "0", "NA", "NA", "0", "NA", "0", "0", "NA", "NA", "NA", "0", "NA", "NA", "NA", "0", "NA", "NA", "0", "NA", "0", "NA", "NA", "NA", "0", "NA", "NA", "0", "0", "NA", "NA", "NA", "0", "NA", "NA", "NA", "NA", "1", "35", "1", "NA", "NA", "46"], ["480705", "Second Half begins Tottenham Hotspur 0, West Ham United 0.", "45'", "0", "0", "0", "0", "1", "0", "0", "NA", "NA", "NA", "NA", "NA", "NA", "NA", "0", "NA", "NA", "0", "NA", "0", "0", "NA", "NA", "NA", "0", "NA", "NA", "NA", "0", "NA", "NA", "0", "NA", "0", "NA", "NA", "NA", "0", "NA", "NA", "0", "0", "NA", "NA", "NA", "0", "NA", "NA", "NA", "NA", "2", "36", "0", "NA", "NA", "45"], ["480705", "Dele Alli (Tottenham Hotspur) wins a free kick in the attacking half.", "51'", "0", "0", "0", "0", "0", "0", "0", "NA", "NA", "NA", "NA", "NA", "NA", "NA", "0", "NA", "NA", "0", "NA", "0", "0", "NA", "NA", "NA", "0", "NA", "NA", "NA", "0", "NA", "NA", "0", "NA", "1", "Dele Alli", "Tottenham Hotspur", "attacking half", "0", "NA", "NA", "0", "0", "NA", "NA", "NA", "0", "NA", "NA", "NA", "NA", "2", "37", "0", "NA", "NA", "51"], ["480705", "Foul by Winston Reid (West Ham United).", "51'", "0", "0", "0", "0", "0", "0", "0", "NA", "NA", "NA", "NA", "NA", "NA", "NA", "1", "Winston Reid", "West Ham United", "0", "NA", "0", "0", "NA", "NA", "NA", "0", "NA", "NA", "NA", "0", "NA", "NA", "0", "NA", "0", "NA", "NA", "NA", "0", "NA", "NA", "0", "0", "NA", "NA", "NA", "0", "NA", "NA", "NA", "NA", "2", "38", "0", "NA", "NA", "51"], ["480705", "Attempt missed. Harry Kane (Tottenham Hotspur) right footed shot from outside the box is high and wide to the right. Assisted by Dele Alli.", "52'", "0", "0", "0", "0", "0", "1", "0", "missed", "Harry Kane", "Tottenham Hotspur", "right", "outside the box", "high and wide to the right", "Dele Alli", "0", "NA", "NA", "0", "NA", "0", "0", "NA", "NA", "NA", "0", "NA", "NA", "NA", "0", "NA", "NA", "0", "NA", "0", "NA", "NA", "NA", "0", "NA", "NA", "0", "0", "NA", "NA", "NA", "0", "NA", "NA", "NA", "NA", "2", "39", "0", "NA", "NA", "52"], ["480705", "Foul by Dele Alli (Tottenham Hotspur).", "55'", "0", "0", "0", "0", "0", "0", "0", "NA", "NA", "NA", "NA", "NA", "NA", "NA", "1", "Dele Alli", "Tottenham Hotspur", "0", "NA", "0", "0", "NA", "NA", "NA", "0", "NA", "NA", "NA", "0", "NA", "NA", "0", "NA", "0", "NA", "NA", "NA", "0", "NA", "NA", "0", "0", "NA", "NA", "NA", "0", "NA", "NA", "NA", "NA", "2", "40", "0", "NA", "NA", "55"], ["480705", "Pedro Obiang (West Ham United) wins a free kick in the defensive half.", "55'", "0", "0", "0", "0", "0", "0", "0", "NA", "NA", "NA", "NA", "NA", "NA", "NA", "0", "NA", "NA", "0", "NA", "0", "0", "NA", "NA", "NA", "0", "NA", "NA", "NA", "0", "NA", "NA", "0", "NA", "1", "Pedro Obiang", "West Ham United", "defensive half", "0", "NA", "NA", "0", "0", "NA", "NA", "NA", "0", "NA", "NA", "NA", "NA", "2", "41", "0", "NA", "NA", "55"], ["480705", "Offside, West Ham United. Adrián tries a through ball, but Manuel Lanzini is caught offside.", "56'", "0", "0", "0", "0", "0", "0", "0", "NA", "NA", "NA", "NA", "NA", "NA", "NA", "0", "NA", "NA", "0", "NA", "0", "1", "West Ham United", "Manuel Lanzini", "Adrián", "0", "NA", "NA", "NA", "0", "NA", "NA", "0", "NA", "0", "NA", "NA", "NA", "0", "NA", "NA", "0", "0", "NA", "NA", "NA", "0", "NA", "NA", "NA", "NA", "2", "42", "0", "NA", "NA", "56"], ["480705", "Attempt blocked. Son Heung-Min (Tottenham Hotspur) right footed shot from the centre of the box is blocked.", "58'", "0", "0", "0", "0", "0", "1", "0", "blocked", "Son Heung-Min", "Tottenham Hotspur", "right", "the centre of the box", "NA", "NA", "0", "NA", "NA", "0", "NA", "0", "0", "NA", "NA", "NA", "0", "NA", "NA", "NA", "0", "NA", "NA", "0", "NA", "0", "NA", "NA", "NA", "0", "NA", "NA", "0", "0", "NA", "NA", "NA", "0", "NA", "NA", "NA", "NA", "2", "43", "0", "NA", "NA", "58"], ["480705", "Ben Davies (Tottenham Hotspur) wins a free kick in the defensive half.", "59'", "0", "0", "0", "0", "0", "0", "0", "NA", "NA", "NA", "NA", "NA", "NA", "NA", "0", "NA", "NA", "0", "NA", "0", "0", "NA", "NA", "NA", "0", "NA", "NA", "NA", "0", "NA", "NA", "0", "NA", "1", "Ben Davies", "Tottenham Hotspur", "defensive half", "0", "NA", "NA", "0", "0", "NA", "NA", "NA", "0", "NA", "NA", "NA", "NA", "2", "44", "0", "NA", "NA", "59"], ["480705", "Foul by Cheikhou Kouyaté (West Ham United).", "59'", "0", "0", "0", "0", "0", "0", "0", "NA", "NA", "NA", "NA", "NA", "NA", "NA", "1", "Cheikhou Kouyaté", "West Ham United", "0", "NA", "0", "0", "NA", "NA", "NA", "0", "NA", "NA", "NA", "0", "NA", "NA", "0", "NA", "0", "NA", "NA", "NA", "0", "NA", "NA", "0", "0", "NA", "NA", "NA", "0", "NA", "NA", "NA", "NA", "2", "45", "0", "NA", "NA", "59"], ["480705", "Attempt blocked. Christian Eriksen (Tottenham Hotspur) right footed shot from the centre of the box is blocked.", "61'", "0", "0", "0", "0", "0", "1", "0", "blocked", "Christian Eriksen", "Tottenham Hotspur", "right", "the centre of the box", "NA", "NA", "0", "NA", "NA", "0", "NA", "0", "0", "NA", "NA", "NA", "0", "NA", "NA", "NA", "0", "NA", "NA", "0", "NA", "0", "NA", "NA", "NA", "0", "NA", "NA", "0", "0", "NA", "NA", "NA", "0", "NA", "NA", "NA", "NA", "2", "46", "0", "NA", "NA", "61"], ["480705", "Attempt missed. Dele Alli (Tottenham Hotspur) header from the centre of the box is close, but misses to the right. Assisted by Ben Davies.", "61'", "0", "0", "0", "0", "0", "1", "0", "missed", "Dele Alli", "Tottenham Hotspur", "header", "the centre of the box", "close, but right", "Ben Davies", "0", "NA", "NA", "0", "NA", "0", "0", "NA", "NA", "NA", "0", "NA", "NA", "NA", "0", "NA", "NA", "0", "NA", "0", "NA", "NA", "NA", "0", "NA", "NA", "0", "0", "NA", "NA", "NA", "0", "NA", "NA", "NA", "NA", "2", "47", "0", "NA", "NA", "61"], ["480705", "Offside, Tottenham Hotspur. Son Heung-Min tries a through ball, but Harry Kane is caught offside.", "63'", "0", "0", "0", "0", "0", "0", "0", "NA", "NA", "NA", "NA", "NA", "NA", "NA", "0", "NA", "NA", "0", "NA", "0", "1", "Tottenham Hotspur", "Harry Kane", "Son Heung-Min", "0", "NA", "NA", "NA", "0", "NA", "NA", "0", "NA", "0", "NA", "NA", "NA", "0", "NA", "NA", "0", "0", "NA", "NA", "NA", "0", "NA", "NA", "NA", "NA", "2", "48", "0", "NA", "NA", "63"], ["480705", "Attempt blocked. Jan Vertonghen (Tottenham Hotspur) left footed shot from outside the box is blocked. Assisted by Davinson Sánchez.", "64'", "0", "0", "0", "0", "0", "1", "0", "blocked", "Jan Vertonghen", "Tottenham Hotspur", "left", "outside the box", "NA", "Davinson Sánchez", "0", "NA", "NA", "0", "NA", "0", "0", "NA", "NA", "NA", "0", "NA", "NA", "NA", "0", "NA", "NA", "0", "NA", "0", "NA", "NA", "NA", "0", "NA", "NA", "0", "0", "NA", "NA", "NA", "0", "NA", "NA", "NA", "NA", "2", "49", "0", "NA", "NA", "64"], ["480705", "Offside, Tottenham Hotspur. Jan Vertonghen tries a through ball, but Harry Kane is caught offside.", "64'", "0", "0", "0", "0", "0", "0", "0", "NA", "NA", "NA", "NA", "NA", "NA", "NA", "0", "NA", "NA", "0", "NA", "0", "1", "Tottenham Hotspur", "Harry Kane", "Jan Vertonghen", "0", "NA", "NA", "NA", "0", "NA", "NA", "0", "NA", "0", "NA", "NA", "NA", "0", "NA", "NA", "0", "0", "NA", "NA", "NA", "0", "NA", "NA", "NA", "NA", "2", "50", "0", "NA", "NA", "64"], ["480705", "Substitution, West Ham United. André Ayew replaces Chicharito.", "64'", "0", "0", "0", "0", "0", "0", "0", "NA", "NA", "NA", "NA", "NA", "NA", "NA", "0", "NA", "NA", "0", "NA", "0", "0", "NA", "NA", "NA", "0", "NA", "NA", "NA", "0", "NA", "NA", "0", "NA", "0", "NA", "NA", "NA", "0", "NA", "NA", "1", "0", "West Ham United", "André Ayew", "Chicharito", "0", "NA", "NA", "NA", "NA", "2", "51", "0", "NA", "NA", "64"], ["480705", "Attempt saved. Christian Eriksen (Tottenham Hotspur) right footed shot from outside the box is saved in the bottom left corner. Assisted by Ben Davies.", "66'", "0", "0", "0", "0", "0", "1", "0", "saved", "Christian Eriksen", "Tottenham Hotspur", "right", "outside the box", "the bottom left corner", "Ben Davies", "0", "NA", "NA", "0", "NA", "0", "0", "NA", "NA", "NA", "0", "NA", "NA", "NA", "0", "NA", "NA", "0", "NA", "0", "NA", "NA", "NA", "0", "NA", "NA", "0", "0", "NA", "NA", "NA", "0", "NA", "NA", "NA", "NA", "2", "52", "0", "NA", "NA", "66"], ["480705", "Attempt blocked. Harry Kane (Tottenham Hotspur) left footed shot from the centre of the box is blocked. Assisted by Christian Eriksen with a through ball.", "67'", "0", "0", "0", "0", "0", "1", "0", "blocked", "Harry Kane", "Tottenham Hotspur", "left", "the centre of the box", "NA", "Christian Eriksen", "0", "NA", "NA", "0", "through", "0", "0", "NA", "NA", "NA", "0", "NA", "NA", "NA", "0", "NA", "NA", "0", "NA", "0", "NA", "NA", "NA", "0", "NA", "NA", "0", "0", "NA", "NA", "NA", "0", "NA", "NA", "NA", "NA", "2", "53", "0", "NA", "NA", "67"], ["480705", "Attempt missed. Dele Alli (Tottenham Hotspur) header from very close range is too high.", "67'", "0", "0", "0", "0", "0", "1", "0", "missed", "Dele Alli", "Tottenham Hotspur", "header", "very close range", "too high", "NA", "0", "NA", "NA", "0", "NA", "0", "0", "NA", "NA", "NA", "0", "NA", "NA", "NA", "0", "NA", "NA", "0", "NA", "0", "NA", "NA", "NA", "0", "NA", "NA", "0", "0", "NA", "NA", "NA", "0", "NA", "NA", "NA", "NA", "2", "54", "0", "NA", "NA", "67"], ["480705", "Foul by Cheikhou Kouyaté (West Ham United).", "69'", "0", "0", "0", "0", "0", "0", "0", "NA", "NA", "NA", "NA", "NA", "NA", "NA", "1", "Cheikhou Kouyaté", "West Ham United", "0", "NA", "0", "0", "NA", "NA", "NA", "0", "NA", "NA", "NA", "0", "NA", "NA", "0", "NA", "0", "NA", "NA", "NA", "0", "NA", "NA", "0", "0", "NA", "NA", "NA", "0", "NA", "NA", "NA", "NA", "2", "55", "0", "NA", "NA", "69"], ["480705", "Son Heung-Min (Tottenham Hotspur) wins a free kick in the defensive half.", "69'", "0", "0", "0", "0", "0", "0", "0", "NA", "NA", "NA", "NA", "NA", "NA", "NA", "0", "NA", "NA", "0", "NA", "0", "0", "NA", "NA", "NA", "0", "NA", "NA", "NA", "0", "NA", "NA", "0", "NA", "1", "Son Heung-Min", "Tottenham Hotspur", "defensive half", "0", "NA", "NA", "0", "0", "NA", "NA", "NA", "0", "NA", "NA", "NA", "NA", "2", "56", "0", "NA", "NA", "69"], ["480705", "Goal!  Tottenham Hotspur 0, West Ham United 1. Pedro Obiang (West Ham United) right footed shot from outside the box to the top left corner. Assisted by Manuel Lanzini.", "70'", "0", "1", "0", "0", "0", "1", "0", "goal", "Pedro Obiang", "West Ham United", "right", "outside the box", "top left corner", "Manuel Lanzini", "0", "NA", "NA", "0", "NA", "0", "0", "NA", "NA", "NA", "0", "NA", "NA", "NA", "0", "NA", "NA", "0", "NA", "0", "NA", "NA", "NA", "0", "NA", "NA", "0", "0", "NA", "NA", "NA", "0", "NA", "NA", "NA", "NA", "2", "57", "0", "NA", "NA", "70"], ["480705", "Attempt saved. Harry Kane (Tottenham Hotspur) right footed shot from a difficult angle on the right is saved in the bottom left corner.", "72'", "0", "1", "0", "0", "0", "1", "0", "saved", "Harry Kane", "Tottenham Hotspur", "right", "NA", "the bottom left corner", "NA", "0", "NA", "NA", "0", "NA", "0", "0", "NA", "NA", "NA", "0", "NA", "NA", "NA", "0", "NA", "NA", "0", "NA", "0", "NA", "NA", "NA", "0", "NA", "NA", "0", "0", "NA", "NA", "NA", "0", "NA", "NA", "NA", "NA", "2", "58", "0", "NA", "NA", "72"], ["480705", "Corner,  Tottenham Hotspur. Conceded by Adrián.", "72'", "0", "1", "0", "0", "0", "0", "0", "NA", "NA", "NA", "NA", "NA", "NA", "NA", "0", "NA", "NA", "0", "NA", "0", "0", "NA", "NA", "NA", "0", "NA", "NA", "NA", "0", "NA", "NA", "0", "NA", "0", "NA", "NA", "NA", "1", "Tottenham Hotspur", "Adrián", "0", "0", "NA", "NA", "NA", "0", "NA", "NA", "NA", "NA", "2", "59", "0", "NA", "NA", "72"], ["480705", "Attempt saved. Harry Kane (Tottenham Hotspur) left footed shot from the left side of the box is saved in the centre of the goal. Assisted by Jan Vertonghen.", "73'", "0", "1", "0", "0", "0", "1", "0", "saved", "Harry Kane", "Tottenham Hotspur", "left", "the left side of the box", "the centre of the goal", "Jan Vertonghen", "0", "NA", "NA", "0", "NA", "0", "0", "NA", "NA", "NA", "0", "NA", "NA", "NA", "0", "NA", "NA", "0", "NA", "0", "NA", "NA", "NA", "0", "NA", "NA", "0", "0", "NA", "NA", "NA", "0", "NA", "NA", "NA", "NA", "2", "60", "0", "NA", "NA", "73"], ["480705", "Substitution, Tottenham Hotspur. Erik Lamela replaces Moussa Sissoko.", "74'", "0", "1", "0", "0", "0", "0", "0", "NA", "NA", "NA", "NA", "NA", "NA", "NA", "0", "NA", "NA", "0", "NA", "0", "0", "NA", "NA", "NA", "0", "NA", "NA", "NA", "0", "NA", "NA", "0", "NA", "0", "NA", "NA", "NA", "0", "NA", "NA", "1", "0", "Tottenham Hotspur", "Erik Lamela", "Moussa Sissoko", "0", "NA", "NA", "NA", "NA", "2", "61", "0", "NA", "NA", "74"], ["480705", "Substitution, Tottenham Hotspur. Victor Wanyama replaces Eric Dier.", "74'", "0", "1", "0", "0", "0", "0", "0", "NA", "NA", "NA", "NA", "NA", "NA", "NA", "0", "NA", "NA", "0", "NA", "0", "0", "NA", "NA", "NA", "0", "NA", "NA", "NA", "0", "NA", "NA", "0", "NA", "0", "NA", "NA", "NA", "0", "NA", "NA", "1", "0", "Tottenham Hotspur", "Victor Wanyama", "Eric Dier", "0", "NA", "NA", "NA", "NA", "2", "62", "0", "NA", "NA", "74"], ["480705", "Attempt saved. Christian Eriksen (Tottenham Hotspur) right footed shot from outside the box is saved in the bottom left corner. Assisted by Son Heung-Min.", "75'", "0", "1", "0", "0", "0", "1", "0", "saved", "Christian Eriksen", "Tottenham Hotspur", "right", "outside the box", "the bottom left corner", "Son Heung-Min", "0", "NA", "NA", "0", "NA", "0", "0", "NA", "NA", "NA", "0", "NA", "NA", "NA", "0", "NA", "NA", "0", "NA", "0", "NA", "NA", "NA", "0", "NA", "NA", "0", "0", "NA", "NA", "NA", "0", "NA", "NA", "NA", "NA", "2", "63", "0", "NA", "NA", "75"], ["480705", "Foul by Davinson Sánchez (Tottenham Hotspur).", "76'", "0", "1", "0", "0", "0", "0", "0", "NA", "NA", "NA", "NA", "NA", "NA", "NA", "1", "Davinson Sánchez", "Tottenham Hotspur", "0", "NA", "0", "0", "NA", "NA", "NA", "0", "NA", "NA", "NA", "0", "NA", "NA", "0", "NA", "0", "NA", "NA", "NA", "0", "NA", "NA", "0", "0", "NA", "NA", "NA", "0", "NA", "NA", "NA", "NA", "2", "64", "0", "NA", "NA", "76"], ["480705", "Mark Noble (West Ham United) wins a free kick on the right wing.", "76'", "0", "1", "0", "0", "0", "0", "0", "NA", "NA", "NA", "NA", "NA", "NA", "NA", "0", "NA", "NA", "0", "NA", "0", "0", "NA", "NA", "NA", "0", "NA", "NA", "NA", "0", "NA", "NA", "0", "NA", "1", "Mark Noble", "West Ham United", "NA", "0", "NA", "NA", "0", "0", "NA", "NA", "NA", "0", "NA", "NA", "NA", "NA", "2", "65", "0", "NA", "NA", "76"], ["480705", "Attempt missed. Cheikhou Kouyaté (West Ham United) header from the right side of the six yard box is close, but misses to the right. Assisted by Pedro Obiang with a cross following a set piece situation.", "77'", "0", "1", "0", "0", "0", "1", "0", "missed", "Cheikhou Kouyaté", "West Ham United", "header", "the right side of the six yard box", "close, but right", "Pedro Obiang", "0", "NA", "NA", "1", "cross", "0", "0", "NA", "NA", "NA", "0", "NA", "NA", "NA", "0", "NA", "NA", "0", "NA", "0", "NA", "NA", "NA", "0", "NA", "NA", "0", "0", "NA", "NA", "NA", "0", "NA", "NA", "NA", "NA", "2", "66", "0", "NA", "NA", "77"], ["480705", "Foul by Erik Lamela (Tottenham Hotspur).", "79'", "0", "1", "0", "0", "0", "0", "0", "NA", "NA", "NA", "NA", "NA", "NA", "NA", "1", "Erik Lamela", "Tottenham Hotspur", "0", "NA", "0", "0", "NA", "NA", "NA", "0", "NA", "NA", "NA", "0", "NA", "NA", "0", "NA", "0", "NA", "NA", "NA", "0", "NA", "NA", "0", "0", "NA", "NA", "NA", "0", "NA", "NA", "NA", "NA", "2", "67", "0", "NA", "NA", "79"], ["480705", "Winston Reid (West Ham United) wins a free kick in the defensive half.", "79'", "0", "1", "0", "0", "0", "0", "0", "NA", "NA", "NA", "NA", "NA", "NA", "NA", "0", "NA", "NA", "0", "NA", "0", "0", "NA", "NA", "NA", "0", "NA", "NA", "NA", "0", "NA", "NA", "0", "NA", "1", "Winston Reid", "West Ham United", "defensive half", "0", "NA", "NA", "0", "0", "NA", "NA", "NA", "0", "NA", "NA", "NA", "NA", "2", "68", "0", "NA", "NA", "79"], ["480705", "Corner,  Tottenham Hotspur. Conceded by Declan Rice.", "82'", "0", "1", "0", "0", "0", "0", "0", "NA", "NA", "NA", "NA", "NA", "NA", "NA", "0", "NA", "NA", "0", "NA", "0", "0", "NA", "NA", "NA", "0", "NA", "NA", "NA", "0", "NA", "NA", "0", "NA", "0", "NA", "NA", "NA", "1", "Tottenham Hotspur", "Declan Rice", "0", "0", "NA", "NA", "NA", "0", "NA", "NA", "NA", "NA", "2", "69", "0", "NA", "NA", "82"], ["480705", "Substitution, Tottenham Hotspur. Fernando Llorente replaces Ben Davies.", "82'", "0", "1", "0", "0", "0", "0", "0", "NA", "NA", "NA", "NA", "NA", "NA", "NA", "0", "NA", "NA", "0", "NA", "0", "0", "NA", "NA", "NA", "0", "NA", "NA", "NA", "0", "NA", "NA", "0", "NA", "0", "NA", "NA", "NA", "0", "NA", "NA", "1", "0", "Tottenham Hotspur", "Fernando Llorente", "Ben Davies", "0", "NA", "NA", "NA", "NA", "2", "70", "0", "NA", "NA", "82"], ["480705", "Attempt blocked. Jan Vertonghen (Tottenham Hotspur) left footed shot from the left side of the box is blocked.", "83'", "0", "1", "0", "0", "0", "1", "0", "blocked", "Jan Vertonghen", "Tottenham Hotspur", "left", "the left side of the box", "NA", "NA", "0", "NA", "NA", "0", "NA", "0", "0", "NA", "NA", "NA", "0", "NA", "NA", "NA", "0", "NA", "NA", "0", "NA", "0", "NA", "NA", "NA", "0", "NA", "NA", "0", "0", "NA", "NA", "NA", "0", "NA", "NA", "NA", "NA", "2", "71", "0", "NA", "NA", "83"], ["480705", "Corner,  Tottenham Hotspur. Conceded by Cheikhou Kouyaté.", "83'", "0", "1", "0", "0", "0", "0", "0", "NA", "NA", "NA", "NA", "NA", "NA", "NA", "0", "NA", "NA", "0", "NA", "0", "0", "NA", "NA", "NA", "0", "NA", "NA", "NA", "0", "NA", "NA", "0", "NA", "0", "NA", "NA", "NA", "1", "Tottenham Hotspur", "Cheikhou Kouyaté", "0", "0", "NA", "NA", "NA", "0", "NA", "NA", "NA", "NA", "2", "72", "0", "NA", "NA", "83"], ["480705", "Attempt missed. Victor Wanyama (Tottenham Hotspur) right footed shot from the centre of the box misses to the right following a corner.", "83'", "0", "1", "0", "0", "0", "1", "0", "missed", "Victor Wanyama", "Tottenham Hotspur", "right", "the centre of the box", "right", "NA", "0", "NA", "NA", "0", "NA", "1", "0", "NA", "NA", "NA", "0", "NA", "NA", "NA", "0", "NA", "NA", "0", "NA", "0", "NA", "NA", "NA", "0", "NA", "NA", "0", "0", "NA", "NA", "NA", "0", "NA", "NA", "NA", "NA", "2", "73", "0", "NA", "NA", "83"], ["480705", "Goal!  Tottenham Hotspur 1, West Ham United 1. Son Heung-Min (Tottenham Hotspur) right footed shot from outside the box to the top right corner. Assisted by Erik Lamela.", "84'", "1", "1", "0", "0", "0", "1", "0", "goal", "Son Heung-Min", "Tottenham Hotspur", "right", "outside the box", "top right corner", "Erik Lamela", "0", "NA", "NA", "0", "NA", "0", "0", "NA", "NA", "NA", "0", "NA", "NA", "NA", "0", "NA", "NA", "0", "NA", "0", "NA", "NA", "NA", "0", "NA", "NA", "0", "0", "NA", "NA", "NA", "0", "NA", "NA", "NA", "NA", "2", "74", "0", "NA", "NA", "84"], ["480705", "Substitution, West Ham United. Andy Carroll replaces Manuel Lanzini.", "85'", "1", "1", "0", "0", "0", "0", "0", "NA", "NA", "NA", "NA", "NA", "NA", "NA", "0", "NA", "NA", "0", "NA", "0", "0", "NA", "NA", "NA", "0", "NA", "NA", "NA", "0", "NA", "NA", "0", "NA", "0", "NA", "NA", "NA", "0", "NA", "NA", "1", "0", "West Ham United", "Andy Carroll", "Manuel Lanzini", "0", "NA", "NA", "NA", "NA", "2", "75", "0", "NA", "NA", "85"], ["480705", "Attempt missed. André Ayew (West Ham United) left footed shot from a difficult angle on the left is close, but misses to the right. Assisted by Arthur Masuaku.", "86'", "1", "1", "0", "0", "0", "1", "0", "missed", "André Ayew", "West Ham United", "left", "NA", "NA", "Arthur Masuaku", "0", "NA", "NA", "0", "NA", "0", "0", "NA", "NA", "NA", "0", "NA", "NA", "NA", "0", "NA", "NA", "0", "NA", "0", "NA", "NA", "NA", "0", "NA", "NA", "0", "0", "NA", "NA", "NA", "0", "NA", "NA", "NA", "NA", "2", "76", "0", "NA", "NA", "86"], ["480705", "Corner,  West Ham United. Conceded by Hugo Lloris.", "86'", "1", "1", "0", "0", "0", "0", "0", "NA", "NA", "NA", "NA", "NA", "NA", "NA", "0", "NA", "NA", "0", "NA", "0", "0", "NA", "NA", "NA", "0", "NA", "NA", "NA", "0", "NA", "NA", "0", "NA", "0", "NA", "NA", "NA", "1", "West Ham United", "Hugo Lloris", "0", "0", "NA", "NA", "NA", "0", "NA", "NA", "NA", "NA", "2", "77", "0", "NA", "NA", "86"], ["480705", "Offside, West Ham United. Pablo Zabaleta tries a through ball, but Andy Carroll is caught offside.", "87'", "1", "1", "0", "0", "0", "0", "0", "NA", "NA", "NA", "NA", "NA", "NA", "NA", "0", "NA", "NA", "0", "NA", "0", "1", "West Ham United", "Andy Carroll", "Pablo Zabaleta", "0", "NA", "NA", "NA", "0", "NA", "NA", "0", "NA", "0", "NA", "NA", "NA", "0", "NA", "NA", "0", "0", "NA", "NA", "NA", "0", "NA", "NA", "NA", "NA", "2", "78", "0", "NA", "NA", "87"], ["480705", "Andy Carroll (West Ham United) is shown the yellow card.", "87'", "1", "1", "0", "0", "0", "0", "0", "NA", "NA", "NA", "NA", "NA", "NA", "NA", "0", "NA", "NA", "0", "NA", "0", "0", "NA", "NA", "NA", "1", "yellow", "Andy Carroll", "West Ham United", "0", "NA", "NA", "0", "NA", "0", "NA", "NA", "NA", "0", "NA", "NA", "0", "0", "NA", "NA", "NA", "0", "NA", "NA", "NA", "NA", "2", "79", "0", "NA", "NA", "87"], ["480705", "Hand ball by Victor Wanyama (Tottenham Hotspur).", "88'", "1", "1", "0", "0", "0", "0", "0", "NA", "NA", "NA", "NA", "NA", "NA", "NA", "0", "NA", "NA", "0", "NA", "0", "0", "NA", "NA", "NA", "0", "NA", "NA", "NA", "0", "NA", "NA", "0", "NA", "0", "NA", "NA", "NA", "0", "NA", "NA", "0", "0", "NA", "NA", "NA", "0", "NA", "NA", "NA", "NA", "2", "80", "0", "NA", "NA", "88"], ["480705", "Attempt blocked. Fernando Llorente (Tottenham Hotspur) right footed shot from outside the box is blocked. Assisted by Harry Kane.", "89'", "1", "1", "0", "0", "0", "1", "0", "blocked", "Fernando Llorente", "Tottenham Hotspur", "right", "outside the box", "NA", "Harry Kane", "0", "NA", "NA", "0", "NA", "0", "0", "NA", "NA", "NA", "0", "NA", "NA", "NA", "0", "NA", "NA", "0", "NA", "0", "NA", "NA", "NA", "0", "NA", "NA", "0", "0", "NA", "NA", "NA", "0", "NA", "NA", "NA", "NA", "2", "81", "0", "NA", "NA", "89"], ["480705", "Fernando Llorente (Tottenham Hotspur) wins a free kick on the right wing.", "90'", "1", "1", "0", "0", "0", "0", "0", "NA", "NA", "NA", "NA", "NA", "NA", "NA", "0", "NA", "NA", "0", "NA", "0", "0", "NA", "NA", "NA", "0", "NA", "NA", "NA", "0", "NA", "NA", "0", "NA", "1", "Fernando Llorente", "Tottenham Hotspur", "NA", "0", "NA", "NA", "0", "0", "NA", "NA", "NA", "0", "NA", "NA", "NA", "NA", "2", "82", "0", "NA", "NA", "90"], ["480705", "Foul by Mark Noble (West Ham United).", "90'", "1", "1", "0", "0", "0", "0", "0", "NA", "NA", "NA", "NA", "NA", "NA", "NA", "1", "Mark Noble", "West Ham United", "0", "NA", "0", "0", "NA", "NA", "NA", "0", "NA", "NA", "NA", "0", "NA", "NA", "0", "NA", "0", "NA", "NA", "NA", "0", "NA", "NA", "0", "0", "NA", "NA", "NA", "0", "NA", "NA", "NA", "NA", "2", "83", "0", "NA", "NA", "90"], ["480705", "Mark Noble (West Ham United) is shown the yellow card for a bad foul.", "90'", "1", "1", "0", "0", "0", "0", "0", "NA", "NA", "NA", "NA", "NA", "NA", "NA", "0", "NA", "NA", "0", "NA", "0", "0", "NA", "NA", "NA", "1", "yellow", "Mark Noble", "West Ham United", "0", "NA", "NA", "0", "NA", "0", "NA", "NA", "NA", "0", "NA", "NA", "0", "0", "NA", "NA", "NA", "0", "NA", "NA", "NA", "NA", "2", "84", "0", "NA", "NA", "90"], ["480705", "Foul by Fernando Llorente (Tottenham Hotspur).", "90'+1'", "1", "1", "0", "0", "0", "0", "0", "NA", "NA", "NA", "NA", "NA", "NA", "NA", "1", "Fernando Llorente", "Tottenham Hotspur", "0", "NA", "0", "0", "NA", "NA", "NA", "0", "NA", "NA", "NA", "0", "NA", "NA", "0", "NA", "0", "NA", "NA", "NA", "0", "NA", "NA", "0", "0", "NA", "NA", "NA", "0", "NA", "NA", "NA", "NA", "2", "85", "1", "NA", "NA", "91"], ["480705", "Winston Reid (West Ham United) wins a free kick in the defensive half.", "90'+1'", "1", "1", "0", "0", "0", "0", "0", "NA", "NA", "NA", "NA", "NA", "NA", "NA", "0", "NA", "NA", "0", "NA", "0", "0", "NA", "NA", "NA", "0", "NA", "NA", "NA", "0", "NA", "NA", "0", "NA", "1", "Winston Reid", "West Ham United", "defensive half", "0", "NA", "NA", "0", "0", "NA", "NA", "NA", "0", "NA", "NA", "NA", "NA", "2", "86", "1", "NA", "NA", "91"], ["480705", "Attempt blocked. Son Heung-Min (Tottenham Hotspur) right footed shot from the centre of the box is blocked.", "90'+4'", "1", "1", "0", "0", "0", "1", "0", "blocked", "Son Heung-Min", "Tottenham Hotspur", "right", "the centre of the box", "NA", "NA", "0", "NA", "NA", "0", "NA", "0", "0", "NA", "NA", "NA", "0", "NA", "NA", "NA", "0", "NA", "NA", "0", "NA", "0", "NA", "NA", "NA", "0", "NA", "NA", "0", "0", "NA", "NA", "NA", "0", "NA", "NA", "NA", "NA", "2", "87", "1", "NA", "NA", "94"], ["480705", "Attempt blocked. Victor Wanyama (Tottenham Hotspur) right footed shot from outside the box is blocked.", "90'+4'", "1", "1", "0", "0", "0", "1", "0", "blocked", "Victor Wanyama", "Tottenham Hotspur", "right", "outside the box", "NA", "NA", "0", "NA", "NA", "0", "NA", "0", "0", "NA", "NA", "NA", "0", "NA", "NA", "NA", "0", "NA", "NA", "0", "NA", "0", "NA", "NA", "NA", "0", "NA", "NA", "0", "0", "NA", "NA", "NA", "0", "NA", "NA", "NA", "NA", "2", "88", "1", "NA", "NA", "94"], ["480705", "Attempt blocked. Dele Alli (Tottenham Hotspur) right footed shot from the left side of the box is blocked.", "90'+4'", "1", "1", "0", "0", "0", "1", "0", "blocked", "Dele Alli", "Tottenham Hotspur", "right", "the left side of the box", "NA", "NA", "0", "NA", "NA", "0", "NA", "0", "0", "NA", "NA", "NA", "0", "NA", "NA", "NA", "0", "NA", "NA", "0", "NA", "0", "NA", "NA", "NA", "0", "NA", "NA", "0", "0", "NA", "NA", "NA", "0", "NA", "NA", "NA", "NA", "2", "89", "1", "NA", "NA", "94"], ["480705", "Attempt blocked. Christian Eriksen (Tottenham Hotspur) right footed shot from outside the box is blocked. Assisted by Dele Alli.", "90'+4'", "1", "1", "0", "0", "0", "1", "0", "blocked", "Christian Eriksen", "Tottenham Hotspur", "right", "outside the box", "NA", "Dele Alli", "0", "NA", "NA", "0", "NA", "0", "0", "NA", "NA", "NA", "0", "NA", "NA", "NA", "0", "NA", "NA", "0", "NA", "0", "NA", "NA", "NA", "0", "NA", "NA", "0", "0", "NA", "NA", "NA", "0", "NA", "NA", "NA", "NA", "2", "90", "1", "NA", "NA", "94"], ["480705", "Second Half ends, Tottenham Hotspur 1, West Ham United 1.", "90'+5'", "1", "1", "1", "0", "0", "0", "0", "NA", "NA", "NA", "NA", "NA", "NA", "NA", "0", "NA", "NA", "0", "NA", "0", "0", "NA", "NA", "NA", "0", "NA", "NA", "NA", "0", "NA", "NA", "0", "NA", "0", "NA", "NA", "NA", "0", "NA", "NA", "0", "0", "NA", "NA", "NA", "0", "NA", "NA", "NA", "NA", "2", "91", "1", "NA", "NA", "95"], ["480705", "Match ends, Tottenham Hotspur 1, West Ham United 1.", "90'+5'", "1", "1", "0", "1", "0", "0", "0", "NA", "NA", "NA", "NA", "NA", "NA", "NA", "0", "NA", "NA", "0", "NA", "0", "0", "NA", "NA", "NA", "0", "NA", "NA", "NA", "0", "NA", "NA", "0", "NA", "0", "NA", "NA", "NA", "0", "NA", "NA", "0", "0", "NA", "NA", "NA", "0", "NA", "NA", "NA", "NA", "2", "92", "1", "NA", "NA", "95"]], "Lineup": {"Home Player 9": "Moussa Sissoko", "Home Player 8": "Davinson Sanchez", "Home Player 5": "Christian Eriksen", "Home Player 4": "Eric Dier", "Home Player 7": "Hugo Lloris", "Home Player 6": "Harry Kane", "Home Player 1": "Dele Alli", "Home Player 3": "Ben Davies", "Home Player 2": "Serge Aurier", "Away Player 8": "Angelo Ogbonna", "Away Player 10": "Declan Rice", "Away Player 11": "Pablo Zabaleta", "Away Player 9": "Winston Reid", "Away Player 1": "Adrian", "Away Player 2": "Chicharito", "Away Player 3": "Cheikhou Kouyate", "Away Player 4": "Manuel Lanzini", "Away Player 5": "Arthur Masuaku", "Away Player 6": "Mark Noble", "Away Player 7": "Pedro Obiang", "Game ID": "g_1_Q1x6wKJo", "Home Player 11": "Jan Vertonghen", "Home Player 10": "Son Heung-min"}}