{"Home Player 9": "Angelo Ogbonna", "Home Player 8": "Pedro Obiang", "Home Player 5": "Manuel Lanzini", "Home Player 4": "Aaron Cresswell", "Home Player 7": "Mark Noble", "Home Player 6": "Arthur Masuaku", "Home Player 1": "Adrian", "Home Player 3": "Marko Arnautovic", "Home Player 2": "Michail Antonio", "Away Player 8": "Eden Hazard", "Away Player 10": "Alvaro Morata", "Away Player 11": "Davide Zappacosta", "Team 1 Name": "West Ham", "Away Player 9": "N'Golo Kant\u00c3\u00a9", "Date": "09-12-2017", "Away Player 1": "Marcos Alonso", "Away Player 2": "Cesar Azpilicueta", "Away Player 3": "Tiemoue Bakayoko", "Away Player 4": "Gary Cahill", "Away Player 5": "Andreas Christensen", "Away Player 6": "Thibaut Courtois", "Away Player 7": "Cesc Fabregas", "Team 2 Name": "Chelsea", "Game ID": "g_1_jNp5qhoq", "Home Player 11": "Pablo Zabaleta", "Home Player 10": "Winston Reid"}